Workbook

Sheet Summary
T1: 10109000006 | AA1: Internal Date | AB1: 46322 | AC1: 46321
T2: 10109000006 | AA2: Calc_Date | AB2: 46322
AA3: ledgr_bal_Dt | AB3: 46321 | AC3: =IF(AB3="",AB2-1,AB3) -> 46321
AA4: stmnt_bal_Dt | AC4: =IF(AB4="",AB2-1,AB4) -> 46321
A7: NATIONAL MICROFINANCE BANK PLC
A8: FINANCE AND CONTROL DEPARTMENT
A9: RECONCILIATION UNIT
A11: RECONCILIATION OF:- | B11: BOT
A12: Currency:- | B12: USD
A13: Reconciliation Date:- | B13: =IF(AB1="",AB2,AB1) -> 46322
A15: =CONCATENATE("Outstanding Items in the Ledger SUMMARY :",T1) -> Outstanding Items in the Ledger SUMMARY :10109000006 | D15: =B12 -> USD
A16: ="Ledger balance as at : " &TEXT(AC3,"dd mmm yyyy") -> Ledger balance as at : 26 Oct 2026 | D16: -10491708
A17: Add. Outstanding credit in the statement | D17: ='External outstanding'!D5 -> 1.9248639e+08
A18: Less. Outstanding debit in the statement | D18: ='External outstanding'!C5 -> 2.6422489e+08
B20: Corrected ledger balance | D20: =D16+D17-D18 -> -82230211
A22: =CONCATENATE("Outstanding Items in the Statement SUMMARY :",T2) -> Outstanding Items in the Statement SUMMARY :10109000006 | D22: =B12 -> USD
A23: ="Statement balance as at : " &TEXT(AC4,"dd mmm yyyy") -> Statement balance as at : 26 Oct 2026 | D23: 34941113
A24: Add:Outstanding debit in the ledger | D24: ='Internal outstanding'!C5 -> 2.5835764e+08
A25: Less. Outstanding credit in the ledger | D25: ='Internal outstanding'!D5 -> 3.7552897e+08
B27: Corrected statement balance | D27: =D23+D24-D25 -> -82230211
B30: Check_Balance | D30: =D20-D27 -> 0
A36: PREPARED BY - CHARLES KAHUNGU | D36: =B13 -> 46322
A40: CHECKED BY - ATHUMANI KATETA | D40: =D36 -> 46322
A44: 1.MANAGER,CARD RECONCILIATION - SAID SUNGURA | D44: =D36 -> 46322
A48: 3.SENIOR MANAGER;RECONCILIATIONS - FRED SAMWEL | D48: =D40 -> 46322

Sheet Internal outstanding
A1: OUTSTANDING ITEMS IN THE G/LEDGER
A5: 46321 | B5: TOTAL | C5: =SUM(C8:C1048576) -> 2.5835764e+08 | D5: =SUM(D8:D1048576) -> 3.7552897e+08
A7: TRN Date | B7: Value Date | C7: DR | D7: CR | E7: TRN Reference | F7: Source Reference | G7: UETR No | H7: Narrative | I7: TXN_ID | J7: END_TO_END_ID | K7: MESSAGE_ID | L7: INSTRIUCTION_ID | M7: OBPM_REFERENCE | N7: BIZ_MSG_ID | O7: GWX_REFERENCE | P7: GWX_UETR | Q7: DCN | R7: EXTERNAL_REF_NO | S7: Aging | T7: AGING GROUP | U7: BOT Classification | V7: Duplicate Mark
A8: 2025/09/07 | B8: 2025/09/05 | C8: 90 | D8: 0 | E8: 101FTIN252500024 | F8: S807039ICP090525 | H8: Sender's Ref: S807039I... | S8: =IF(A8="","",A$5-A8) -> 414 | T8: =IF(S8="","",IF(S8<4,"0-3 Days",IF(S8<31,"4-30 Days",IF(S8<61,"31-60 Days",IF(S8<=90,"61-90 Days",IF(S8>90,"Above 90 Days","0")))))) -> Above 90 Days | U8: =IF(C8="","",IF(C8>0,IF(S8<30,"Normal",IF(S8<60,"Especially Mentioned",IF(S8<90,"Substandard",IF(S8<=180,"Doubtful",IF(S8>180,"Loss","0"))))),"Not Applicable")) -> Loss
A9: 2025/11/05 | B9: 2025/11/03 | C9: 2993 | D9: 0 | E9: 101FTIN253091182 | F9: 2112926307JS | H9: Sender's Ref: 2112926307JS => Ordering Customer: /9130005036570 * 1/RAKBURY ENTERPRISES LIMITED * 2/PLOT NO 3792 KWACHA ROAD OLYMPI P * 3/ZM/LUSAKA => Remittance Info: /ROC/OT25307ZM0180542///URI/TS03 | S9: =IF(A9="","",A$5-A9) -> 355 | T9: =IF(S9="","",IF(S9<4,"0-3 Days",IF(S9<31,"4-30 Days",IF(S9<61,"31-60 Days",IF(S9<=90,"61-90 Days",IF(S9>90,"Above 90 Days","0")))))) -> Above 90 Days | U9: =IF(C9="","",IF(C9>0,IF(S9<30,"Normal",IF(S9<60,"Especially Mentioned",IF(S9<90,"Substandard",IF(S9<=180,"Doubtful",IF(S9>180,"Loss","0"))))),"Not Applicable")) -> Loss
A10: 2025/12/01 | B10: 2025/12/01 | C10: 2580 | D10: 0 | E10: 101FTIN253350501 | F10: 101FTIN253350501 | H10: Sender's Ref: 101FTIN253350501 => Ordering Customer: /10110000001 * TANZTZTXXXX => Remittance Info: //C0153325660501 WACNY2532421441 * //ISN 0057261 OS N 0156605 SSN * //01029858 | S10: =IF(A10="","",A$5-A10) -> 329 | T10: =IF(S10="","",IF(S10<4,"0-3 Days",IF(S10<31,"4-30 Days",IF(S10<61,"31-60 Days",IF(S10<=90,"61-90 Days",IF(S10>90,"Above 90 Days","0")))))) -> Above 90 Days | U10: =IF(C10="","",IF(C10>0,IF(S10<30,"Normal",IF(S10<60,"Especially Mentioned",IF(S10<90,"Substandard",IF(S10<=180,"Doubtful",IF(S10>180,"Loss","0"))))),"Not Applicable")) -> Loss
A11: 2025/12/22 | B11: 2025/12/22 | C11: 93.22 | D11: 0 | E11: 101FTIT253561734 | F11: HZ1JCJLOO6QEB8A2 | H11: Sender's Ref: HZ1JCJLOO6QEB8A2 => Ordering Customer: /250285777701 * 61701 => Remittance Info: T31052025120406 | S11: =IF(A11="","",A$5-A11) -> 308 | T11: =IF(S11="","",IF(S11<4,"0-3 Days",IF(S11<31,"4-30 Days",IF(S11<61,"31-60 Days",IF(S11<=90,"61-90 Days",IF(S11>90,"Above 90 Days","0")))))) -> Above 90 Days | U11: =IF(C11="","",IF(C11>0,IF(S11<30,"Normal",IF(S11<60,"Especially Mentioned",IF(S11<90,"Substandard",IF(S11<=180,"Doubtful",IF(S11>180,"Loss","0"))))),"Not Applicable")) -> Loss
A12: 2025/12/22 | B12: 2025/12/22 | C12: 93.22 | D12: 0 | E12: 101FTIT253561730 | F12: HZ1JCJLREQ9B48EE | H12: Sender's Ref: HZ1JCJLREQ9B48EE => Ordering Customer: /250285777701 * 61701 => Remittance Info: T31052025120404 | S12: =IF(A12="","",A$5-A12) -> 308 | T12: =IF(S12="","",IF(S12<4,"0-3 Days",IF(S12<31,"4-30 Days",IF(S12<61,"31-60 Days",IF(S12<=90,"61-90 Days",IF(S12>90,"Above 90 Days","0")))))) -> Above 90 Days | U12: =IF(C12="","",IF(C12>0,IF(S12<30,"Normal",IF(S12<60,"Especially Mentioned",IF(S12<90,"Substandard",IF(S12<=180,"Doubtful",IF(S12>180,"Loss","0"))))),"Not Applicable")) -> Loss
A13: 2026/01/28 | B13: 2026/01/26 | C13: 46000 | D13: 0 | E13: 101FTIT260281950 | F13: HZ1JFSJVFN0D7B36 | H13: Sender's Ref: HZ1JFSJVFN0D7B36 => Ordering Customer: 10121880593 * SERENE SAFARI BUREAU DE => Remittance Info: Fx Deal | S13: =IF(A13="","",A$5-A13) -> 271 | T13: =IF(S13="","",IF(S13<4,"0-3 Days",IF(S13<31,"4-30 Days",IF(S13<61,"31-60 Days",IF(S13<=90,"61-90 Days",IF(S13>90,"Above 90 Days","0")))))) -> Above 90 Days | U13: =IF(C13="","",IF(C13>0,IF(S13<30,"Normal",IF(S13<60,"Especially Mentioned",IF(S13<90,"Substandard",IF(S13<=180,"Doubtful",IF(S13>180,"Loss","0"))))),"Not Applicable")) -> Loss
A14: 2026/02/03 | B14: 2026/02/03 | C14: 1500 | D14: 0 | E14: 101joj9260340003 | F14: 611FTFV253370001 | H14: RTN 611FTFV253370001 dd03122025 Rsn Invalid Bene details | S14: =IF(A14="","",A$5-A14) -> 265 | T14: =IF(S14="","",IF(S14<4,"0-3 Days",IF(S14<31,"4-30 Days",IF(S14<61,"31-60 Days",IF(S14<=90,"61-90 Days",IF(S14>90,"Above 90 Days","0")))))) -> Above 90 Days | U14: =IF(C14="","",IF(C14>0,IF(S14<30,"Normal",IF(S14<60,"Especially Mentioned",IF(S14<90,"Substandard",IF(S14<=180,"Doubtful",IF(S14>180,"Loss","0"))))),"Not Applicable")) -> Loss
A15: 2026/04/22 | B15: 2026/04/22 | C15: 318.6 | D15: 0 | E15: 101FTIT261126670 | F15: OT26111TZ0193487 | H15: Sender's Ref: OT26111TZ0193487 => Ordering Customer: /9120003165904 => Remittance Info: SEQ 203615 | S15: =IF(A15="","",A$5-A15) -> 187 | T15: =IF(S15="","",IF(S15<4,"0-3 Days",IF(S15<31,"4-30 Days",IF(S15<61,"31-60 Days",IF(S15<=90,"61-90 Days",IF(S15>90,"Above 90 Days","0")))))) -> Above 90 Days | U15: =IF(C15="","",IF(C15>0,IF(S15<30,"Normal",IF(S15<60,"Especially Mentioned",IF(S15<90,"Substandard",IF(S15<=180,"Doubtful",IF(S15>180,"Loss","0"))))),"Not Applicable")) -> Loss
A16: 2026/07/08 | B16: 2026/07/08 | C16: 0 | D16: 20 | E16: 428IBOT261891008 | F16: YUAKGC61R9 | H16: Sender's Ref: YUAKGC61R9 => Ultimate Beneficiary: /9120001520529 * :CMA CGM (TANZANIA) LIMITED => Remittance Info: BL: ISB1881268 | S16: =IF(A16="","",A$5-A16) -> 110 | T16: =IF(S16="","",IF(S16<4,"0-3 Days",IF(S16<31,"4-30 Days",IF(S16<61,"31-60 Days",IF(S16<=90,"61-90 Days",IF(S16>90,"Above 90 Days","0")))))) -> Above 90 Days | U16: =IF(C16="","",IF(C16>0,IF(S16<30,"Normal",IF(S16<60,"Especially Mentioned",IF(S16<90,"Substandard",IF(S16<=180,"Doubtful",IF(S16>180,"Loss","0"))))),"Not Applicable")) -> Not Applicable
A17: 2026/07/25 | B17: 2026/07/24 | C17: 164500 | D17: 0 | E17: 101FTIN262060032 | F17: 2020739205JS | H17: Sender's Ref: 2020739205JS => Ordering Customer: 8911205569 * MAITRI INTERNATIONAL => Remittance Info: /ROC/0642AIR261671028///URI/TWDS IN * V NO HAL26TZ0050 | S17: =IF(A17="","",A$5-A17) -> 93 | T17: =IF(S17="","",IF(S17<4,"0-3 Days",IF(S17<31,"4-30 Days",IF(S17<61,"31-60 Days",IF(S17<=90,"61-90 Days",IF(S17>90,"Above 90 Days","0")))))) -> Above 90 Days | U17: =IF(C17="","",IF(C17>0,IF(S17<30,"Normal",IF(S17<60,"Especially Mentioned",IF(S17<90,"Substandard",IF(S17<=180,"Doubtful",IF(S17>180,"Loss","0"))))),"Not Applicable")) -> Doubtful
A18: 2026/07/29 | B18: 2026/07/29 | C18: 0 | D18: 119.76 | E18: 201IBOT262100039 | F18: RMWHYUDFIU | H18: Sender's Ref: RMWHYUDFIU => Ultimate Beneficiary: /0250299823700 * SHARAF SHIPPING AGENCY (T) LTD => Remittance Info: SHIPPING FEE ESTIM 1931 | S18: =IF(A18="","",A$5-A18) -> 89 | T18: =IF(S18="","",IF(S18<4,"0-3 Days",IF(S18<31,"4-30 Days",IF(S18<61,"31-60 Days",IF(S18<=90,"61-90 Days",IF(S18>90,"Above 90 Days","0")))))) -> 61-90 Days | U18: =IF(C18="","",IF(C18>0,IF(S18<30,"Normal",IF(S18<60,"Especially Mentioned",IF(S18<90,"Substandard",IF(S18<=180,"Doubtful",IF(S18>180,"Loss","0"))))),"Not Applicable")) -> Not Applicable
A19: 2026/07/29 | B19: 2026/07/29 | C19: 0 | D19: 8700 | E19: 801IBOT262100002 | F19: E8NN1M4RMW | H19: Sender's Ref: E8NN1M4RMW => Ultimate Beneficiary: /10412630063 * SALIM HASSAN SHAHA => Remittance Info: Transportation | S19: =IF(A19="","",A$5-A19) -> 89 | T19: =IF(S19="","",IF(S19<4,"0-3 Days",IF(S19<31,"4-30 Days",IF(S19<61,"31-60 Days",IF(S19<=90,"61-90 Days",IF(S19>90,"Above 90 Days","0")))))) -> 61-90 Days | U19: =IF(C19="","",IF(C19>0,IF(S19<30,"Normal",IF(S19<60,"Especially Mentioned",IF(S19<90,"Substandard",IF(S19<=180,"Doubtful",IF(S19>180,"Loss","0"))))),"Not Applicable")) -> Not Applicable
... A23: 2026/08/05 | B23: 2026/08/03 | C23: 7500 | D23: 0 | E23: 206ZEXA2621704NU | F23: GPS-20260803BKIDTZTZP000115 | H23: Incoming Funds Transfer on 05 AUG 26 06.09.01.049428 PM from SREE KRISHNA CARGO LIMITED at . Remarks: TRANSPORT CHARGES FOR 21C CONTOF 500 MT TONS INV NO CIL094 26 | S23: =IF(A23="","",A$5-A23) -> 82 | T23: =IF(S23="","",IF(S23<4,"0-3 Days",IF(S23<31,"4-30 Days",IF(S23<61,"31-60 Days",IF(S23<=90,"61-90 Days",IF(S23>90,"Above 90 Days","0")))))) -> 61-90 Days | U23: =IF(C23="","",IF(C23>0,IF(S23<30,"Normal",IF(S23<60,"Especially Mentioned",IF(S23<90,"Substandard",IF(S23<=180,"Doubtful",IF(S23>180,"Loss","0"))))),"Not Applicable")) -> Substandard
A24: 2026/08/03 | B24: 2026/08/03 | C24: 0 | D24: 300000 | E24: 101o094262150001 | H24: 03 AUG 26 09.59.27.701335 PM => 10109000006 BOT CLEARING USD via OPICS 1081116 ECOBANK USD TZS 2668.00000000 300000.0000 | S24: =IF(A24="","",A$5-A24) -> 84 | T24: =IF(S24="","",IF(S24<4,"0-3 Days",IF(S24<31,"4-30 Days",IF(S24<61,"31-60 Days",IF(S24<=90,"61-90 Days",IF(S24>90,"Above 90 Days","0")))))) -> 61-90 Days | U24: =IF(C24="","",IF(C24>0,IF(S24<30,"Normal",IF(S24<60,"Especially Mentioned",IF(S24<90,"Substandard",IF(S24<=180,"Doubtful",IF(S24>180,"Loss","0"))))),"Not Applicable")) -> Not Applicable
A25: 2026/08/11 | B25: 2026/08/04 | C25: 500000 | D25: 0 | E25: 223ZEXA2622300UY | F25: 2608042608000114 | H25: Incoming Funds Transfer on 11 AUG 26 02.49.33.263674 PM from DIAMOND SHIPPING SERVICES LIMI at . Remarks: TRANSFER TO DSS NMB USD AC | S25: =IF(A25="","",A$5-A25) -> 76 | T25: =IF(S25="","",IF(S25<4,"0-3 Days",IF(S25<31,"4-30 Days",IF(S25<61,"31-60 Days",IF(S25<=90,"61-90 Days",IF(S25>90,"Above 90 Days","0")))))) -> 61-90 Days | U25: =IF(C25="","",IF(C25>0,IF(S25<30,"Normal",IF(S25<60,"Especially Mentioned",IF(S25<90,"Substandard",IF(S25<=180,"Doubtful",IF(S25>180,"Loss","0"))))),"Not Applicable")) -> Substandard
A26: 2026/08/06 | B26: 2026/08/04 | C26: 140 | D26: 0 | E26: 223ZEXA2621800UT | F26: TAPBTZTZ20260804140509662 | H26: Incoming Funds Transfer on 06 AUG 26 07.42.38.767996 PM from GREATLAKES FREIGHT LTD at . Remarks: DEMURRAGE BL GOSUGZH0713334 null | S26: =IF(A26="","",A$5-A26) -> 81 | T26: =IF(S26="","",IF(S26<4,"0-3 Days",IF(S26<31,"4-30 Days",IF(S26<61,"31-60 Days",IF(S26<=90,"61-90 Days",IF(S26>90,"Above 90 Days","0")))))) -> 61-90 Days | U26: =IF(C26="","",IF(C26>0,IF(S26<30,"Normal",IF(S26<60,"Especially Mentioned",IF(S26<90,"Substandard",IF(S26<=180,"Doubtful",IF(S26>180,"Loss","0"))))),"Not Applicable")) -> Substandard
A27: 2026/08/05 | B27: 2026/08/05 | C27: 0 | D27: 959.97 | E27: 403ZEXA26217009V | F27: 2621712038465000 | H27: Outgoing Funds Transfer 05 AUG 26 04.43.05.618888 PM OBDX from ECO LODGE AFRICA LIMITED to Tourism and Public Relations Services Limited 8000421. Remark: Ref email 01072026 | S27: =IF(A27="","",A$5-A27) -> 82 | T27: =IF(S27="","",IF(S27<4,"0-3 Days",IF(S27<31,"4-30 Days",IF(S27<61,"31-60 Days",IF(S27<=90,"61-90 Days",IF(S27>90,"Above 90 Days","0")))))) -> 61-90 Days | U27: =IF(C27="","",IF(C27>0,IF(S27<30,"Normal",IF(S27<60,"Especially Mentioned",IF(S27<90,"Substandard",IF(S27<=180,"Doubtful",IF(S27>180,"Loss","0"))))),"Not Applicable")) -> Not Applicable
A28: 2026/08/05 | B28: 2026/08/05 | C28: 0 | D28: 1348 | E28: 428ZEXA26217007D | F28: 2621723056548000 | H28: Outgoing Funds Transfer 05 AUG 26 03.42.31.418997 PM OBDX from DAMONA TANZANIA SAFARIS LTD to Auric Air Services Ltd 0740425020. Remark: Fam. VdPutten Pnr Ref. 88B96A | S28: =IF(A28="","",A$5-A28) -> 82 | T28: =IF(S28="","",IF(S28<4,"0-3 Days",IF(S28<31,"4-30 Days",IF(S28<61,"31-60 Days",IF(S28<=90,"61-90 Days",IF(S28>90,"Above 90 Days","0")))))) -> 61-90 Days | U28: =IF(C28="","",IF(C28>0,IF(S28<30,"Normal",IF(S28<60,"Especially Mentioned",IF(S28<90,"Substandard",IF(S28<=180,"Doubtful",IF(S28>180,"Loss","0"))))),"Not Applicable")) -> Not Applicable
A29: 2026/08/05 | B29: 2026/08/05 | C29: 0 | D29: 699.37 | E29: 248ZEXA2621700T7 | F29: 2621707058138000 | H29: Outgoing Funds Transfer 05 AUG 26 04.09.02.183224 PM OBDX from APLUS GLOBAL LIMITED to CMA CGM TANZANIA LTD 7045002837. Remark: PORCHARGEGES FOR ZSN0848658A | S29: =IF(A29="","",A$5-A29) -> 82 | T29: =IF(S29="","",IF(S29<4,"0-3 Days",IF(S29<31,"4-30 Days",IF(S29<61,"31-60 Days",IF(S29<=90,"61-90 Days",IF(S29>90,"Above 90 Days","0")))))) -> 61-90 Days | U29: =IF(C29="","",IF(C29>0,IF(S29<30,"Normal",IF(S29<60,"Especially Mentioned",IF(S29<90,"Substandard",IF(S29<=180,"Doubtful",IF(S29>180,"Loss","0"))))),"Not Applicable")) -> Not Applicable
A30: 2026/08/05 | B30: 2026/08/05 | C30: 0 | D30: 85 | E30: 408ZEXA26217006V | F30: 2621706047682000 | H30: Outgoing Funds Transfer 05 AUG 26 04.13.16.025253 PM OBDX from SERENGETI WAKANDA TOURS AND SAFARIS to SANNA ECO LODGE 0026010187. Remark: | S30: =IF(A30="","",A$5-A30) -> 82 | T30: =IF(S30="","",IF(S30<4,"0-3 Days",IF(S30<31,"4-30 Days",IF(S30<61,"31-60 Days",IF(S30<=90,"61-90 Days",IF(S30>90,"Above 90 Days","0")))))) -> 61-90 Days | U30: =IF(C30="","",IF(C30>0,IF(S30<30,"Normal",IF(S30<60,"Especially Mentioned",IF(S30<90,"Substandard",IF(S30<=180,"Doubtful",IF(S30>180,"Loss","0"))))),"Not Applicable")) -> Not Applicable
A31: 2026/08/05 | B31: 2026/08/05 | C31: 0 | D31: 23750 | E31: 602SBRN262170008 | F31: CM3C2A7BCB7779 | H31: Outgoing Funds Transfer 05 AUG 26 03.49.35.868493 PM SYBRIN from SUNSHINE (T) COMPANY LTD to OLK LEMISHAM TRADERS LTD 025083144300. Remark: /BUSINESS | S31: =IF(A31="","",A$5-A31) -> 82 | T31: =IF(S31="","",IF(S31<4,"0-3 Days",IF(S31<31,"4-30 Days",IF(S31<61,"31-60 Days",IF(S31<=90,"61-90 Days",IF(S31>90,"Above 90 Days","0")))))) -> 61-90 Days | U31: =IF(C31="","",IF(C31>0,IF(S31<30,"Normal",IF(S31<60,"Especially Mentioned",IF(S31<90,"Substandard",IF(S31<=180,"Doubtful",IF(S31>180,"Loss","0"))))),"Not Applicable")) -> Not Applicable
A32: 2026/08/05 | B32: 2026/08/05 | C32: 0 | D32: 959.97 | E32: 428ZEXA2621700XJ | F32: 2621714031020000 | H32: Outgoing Funds Transfer 05 AUG 26 04.53.05.150861 PM OBDX from AUGUSTINE'S ADVENTURE AFRICA LTD to Tourism and Public Relations Services Ltd 8000421. Remark: | S32: =IF(A32="","",A$5-A32) -> 82 | T32: =IF(S32="","",IF(S32<4,"0-3 Days",IF(S32<31,"4-30 Days",IF(S32<61,"31-60 Days",IF(S32<=90,"61-90 Days",IF(S32>90,"Above 90 Days","0")))))) -> 61-90 Days | U32: =IF(C32="","",IF(C32>0,IF(S32<30,"Normal",IF(S32<60,"Especially Mentioned",IF(S32<90,"Substandard",IF(S32<=180,"Doubtful",IF(S32>180,"Loss","0"))))),"Not Applicable")) -> Not Applicable
A33: 2026/08/05 | B33: 2026/08/05 | C33: 0 | D33: 1718.5 | E33: 428ZEXA2621700Z7 | F33: 2621708063738000 | H33: Outgoing Funds Transfer 05 AUG 26 05.42.22.679724 PM OBDX from BIG TIME ADVENTURES LIMITED to HERITAGE TENTED CAMPS 0250440170300. Remark: vik Veera accommodation | S33: =IF(A33="","",A$5-A33) -> 82 | T33: =IF(S33="","",IF(S33<4,"0-3 Days",IF(S33<31,"4-30 Days",IF(S33<61,"31-60 Days",IF(S33<=90,"61-90 Days",IF(S33>90,"Above 90 Days","0")))))) -> 61-90 Days | U33: =IF(C33="","",IF(C33>0,IF(S33<30,"Normal",IF(S33<60,"Especially Mentioned",IF(S33<90,"Substandard",IF(S33<=180,"Doubtful",IF(S33>180,"Loss","0"))))),"Not Applicable")) -> Not Applicable
A34: 2026/08/05 | B34: 2026/08/05 | C34: 5000 | D34: 0 | E34: 241ZEXA262170041 | F34: TAPBTZTZ20260805123713345 | H34: Incoming Funds Transfer on 05 AUG 26 12.50.07.035676 PM from Chen Jianshun Fujian at . Remarks: Laan from shareholder | S34: =IF(A34="","",A$5-A34) -> 82 | T34: =IF(S34="","",IF(S34<4,"0-3 Days",IF(S34<31,"4-30 Days",IF(S34<61,"31-60 Days",IF(S34<=90,"61-90 Days",IF(S34>90,"Above 90 Days","0")))))) -> 61-90 Days | U34: =IF(C34="","",IF(C34>0,IF(S34<30,"Normal",IF(S34<60,"Especially Mentioned",IF(S34<90,"Substandard",IF(S34<=180,"Doubtful",IF(S34>180,"Loss","0"))))),"Not Applicable")) -> Substandard
A35: 2026/08/05 | B35: 2026/08/05 | C35: 0 | D35: 1600 | E35: 241ZEXA2621700VG | F35: 2621705036362000 | H35: Outgoing Funds Transfer 05 AUG 26 04.03.39.219027 PM OBDX from SWIN LOGISTICS TANZANIA LIMITED to KORRIDOR TANZANIA LIMITED 025C791250000. Remark: | S35: =IF(A35="","",A$5-A35) -> 82 | T35: =IF(S35="","",IF(S35<4,"0-3 Days",IF(S35<31,"4-30 Days",IF(S35<61,"31-60 Days",IF(S35<=90,"61-90 Days",IF(S35>90,"Above 90 Days","0")))))) -> 61-90 Days | U35: =IF(C35="","",IF(C35>0,IF(S35<30,"Normal",IF(S35<60,"Especially Mentioned",IF(S35<90,"Substandard",IF(S35<=180,"Doubtful",IF(S35>180,"Loss","0"))))),"Not Applicable")) -> Not Applicable
A36: 2026/08/06 | B36: 2026/08/06 | C36: 0 | D36: 925 | E36: 403ZEXA2621800UM | F36: 2621802056580000 | H36: Outgoing Funds Transfer 06 AUG 26 03.43.03.186929 PM OBDX from MAKASA LIMITED to AURIC AIR SERVICES LTD 0740425020. Remark: | S36: =IF(A36="","",A$5-A36) -> 81 | T36: =IF(S36="","",IF(S36<4,"0-3 Days",IF(S36<31,"4-30 Days",IF(S36<61,"31-60 Days",IF(S36<=90,"61-90 Days",IF(S36>90,"Above 90 Days","0")))))) -> 61-90 Days | U36: =IF(C36="","",IF(C36>0,IF(S36<30,"Normal",IF(S36<60,"Especially Mentioned",IF(S36<90,"Substandard",IF(S36<=180,"Doubtful",IF(S36>180,"Loss","0"))))),"Not Applicable")) -> Not Applicable
... A38: 2026/08/06 | B38: 2026/08/06 | C38: 0 | D38: 1278.8 | E38: 234ZEXA26218000X | F38: 2621818065432000 | H38: Outgoing Funds Transfer 06 AUG 26 06.10.41.016964 PM OBDX from BUHAIRAN LIMITED to CORDELIA TOURS(SMC PRIVATE) LIMTED 0987729002. Remark: Cordelia Tours Invoice Payment | S38: =IF(A38="","",A$5-A38) -> 81 | T38: =IF(S38="","",IF(S38<4,"0-3 Days",IF(S38<31,"4-30 Days",IF(S38<61,"31-60 Days",IF(S38<=90,"61-90 Days",IF(S38>90,"Above 90 Days","0")))))) -> 61-90 Days | U38: =IF(C38="","",IF(C38>0,IF(S38<30,"Normal",IF(S38<60,"Especially Mentioned",IF(S38<90,"Substandard",IF(S38<=180,"Doubtful",IF(S38>180,"Loss","0"))))),"Not Applicable")) -> Not Applicable
A39: 2026/08/06 | B39: 2026/08/06 | C39: 0 | D39: 600000 | E39: 101o037262180001 | H39: 06 AUG 26 07.03.54.373621 PM => 10109000006 BOT CLEARING USD via OPICS 2011854 AZANIA | S39: =IF(A39="","",A$5-A39) -> 81 | T39: =IF(S39="","",IF(S39<4,"0-3 Days",IF(S39<31,"4-30 Days",IF(S39<61,"31-60 Days",IF(S39<=90,"61-90 Days",IF(S39>90,"Above 90 Days","0")))))) -> 61-90 Days | U39: =IF(C39="","",IF(C39>0,IF(S39<30,"Normal",IF(S39<60,"Especially Mentioned",IF(S39<90,"Substandard",IF(S39<=180,"Doubtful",IF(S39>180,"Loss","0"))))),"Not Applicable")) -> Not Applicable
A40: 2026/08/06 | B40: 2026/08/06 | C40: 0 | D40: 624.33 | E40: 231ZEXA26218000F | F40: 2621817038744000 | H40: Outgoing Funds Transfer 06 AUG 26 10.45.47.729701 AM OBDX from OLD EXPLORER LTD to TYCHELIMITED 0250214303500. Remark: WB4373 | S40: =IF(A40="","",A$5-A40) -> 81 | T40: =IF(S40="","",IF(S40<4,"0-3 Days",IF(S40<31,"4-30 Days",IF(S40<61,"31-60 Days",IF(S40<=90,"61-90 Days",IF(S40>90,"Above 90 Days","0")))))) -> 61-90 Days | U40: =IF(C40="","",IF(C40>0,IF(S40<30,"Normal",IF(S40<60,"Especially Mentioned",IF(S40<90,"Substandard",IF(S40<=180,"Doubtful",IF(S40>180,"Loss","0"))))),"Not Applicable")) -> Not Applicable
A41: 2026/08/06 | B41: 2026/08/06 | C41: 0 | D41: 52000 | E41: 248ZEXA2621800SV | F41: CMACC3796D106B | H41: Outgoing Funds Transfer 06 AUG 26 03.10.38.831712 PM OBDX from TEAM PARTNER COMPANY LIMITED to NUFAST DELIVERIES 0250379705500. Remark: Fuel payment | S41: =IF(A41="","",A$5-A41) -> 81 | T41: =IF(S41="","",IF(S41<4,"0-3 Days",IF(S41<31,"4-30 Days",IF(S41<61,"31-60 Days",IF(S41<=90,"61-90 Days",IF(S41>90,"Above 90 Days","0")))))) -> 61-90 Days | U41: =IF(C41="","",IF(C41>0,IF(S41<30,"Normal",IF(S41<60,"Especially Mentioned",IF(S41<90,"Substandard",IF(S41<=180,"Doubtful",IF(S41>180,"Loss","0"))))),"Not Applicable")) -> Not Applicable
A42: 2026/08/06 | B42: 2026/08/06 | C42: 0 | D42: 6626 | E42: 408ZEXA262180053 | F42: CM2219D2D1FD12 | H42: Outgoing Funds Transfer 06 AUG 26 12.54.12.133188 PM OBDX from EXTRA PASSION SAFARIS LIMITED to MIGS BUREAU DE CHANGE 02500000U5TB00. Remark: exchange park fee | S42: =IF(A42="","",A$5-A42) -> 81 | T42: =IF(S42="","",IF(S42<4,"0-3 Days",IF(S42<31,"4-30 Days",IF(S42<61,"31-60 Days",IF(S42<=90,"61-90 Days",IF(S42>90,"Above 90 Days","0")))))) -> 61-90 Days | U42: =IF(C42="","",IF(C42>0,IF(S42<30,"Normal",IF(S42<60,"Especially Mentioned",IF(S42<90,"Substandard",IF(S42<=180,"Doubtful",IF(S42>180,"Loss","0"))))),"Not Applicable")) -> Not Applicable
A43: 2026/08/06 | B43: 2026/08/06 | C43: 0 | D43: 7535 | E43: 229ZEXA2621800SL | F43: 2621803039538000 | H43: Outgoing Funds Transfer 06 AUG 26 10.59.01.991577 AM OBDX from TROPICAL TOURS SMC PRIVATE LTD to OCEAN GROUP HOTELS MARKET 0250223524500. Remark: ARR 01 to 08 AUG | S43: =IF(A43="","",A$5-A43) -> 81 | T43: =IF(S43="","",IF(S43<4,"0-3 Days",IF(S43<31,"4-30 Days",IF(S43<61,"31-60 Days",IF(S43<=90,"61-90 Days",IF(S43>90,"Above 90 Days","0")))))) -> 61-90 Days | U43: =IF(C43="","",IF(C43>0,IF(S43<30,"Normal",IF(S43<60,"Especially Mentioned",IF(S43<90,"Substandard",IF(S43<=180,"Doubtful",IF(S43>180,"Loss","0"))))),"Not Applicable")) -> Not Applicable
A44: 2026/08/06 | B44: 2026/08/06 | C44: 0 | D44: 20000 | E44: 206ZEXA26218002L | F44: 2621823055774000 | H44: Outgoing Funds Transfer 06 AUG 26 03.29.37.457466 PM OBDX from SWIFTEX BUREAU DE CHANGE LIMITED to CITIZEN IMPORTEX LIMITED 0400237001. Remark: | S44: =IF(A44="","",A$5-A44) -> 81 | T44: =IF(S44="","",IF(S44<4,"0-3 Days",IF(S44<31,"4-30 Days",IF(S44<61,"31-60 Days",IF(S44<=90,"61-90 Days",IF(S44>90,"Above 90 Days","0")))))) -> 61-90 Days | U44: =IF(C44="","",IF(C44>0,IF(S44<30,"Normal",IF(S44<60,"Especially Mentioned",IF(S44<90,"Substandard",IF(S44<=180,"Doubtful",IF(S44>180,"Loss","0"))))),"Not Applicable")) -> Not Applicable
A45: 2026/08/06 | B45: 2026/08/06 | C45: 0 | D45: 399.18 | E45: 248ZEXA2621800S2 | F45: 000008365959 | H45: Outgoing Funds Transfer 06 AUG 26 10.15.51.879133 AM OBDX from BEST OCEANAIR (T) LTD to GENUINE FREIGHT SERVICES LIMITED 0100000441467. Remark: | S45: =IF(A45="","",A$5-A45) -> 81 | T45: =IF(S45="","",IF(S45<4,"0-3 Days",IF(S45<31,"4-30 Days",IF(S45<61,"31-60 Days",IF(S45<=90,"61-90 Days",IF(S45>90,"Above 90 Days","0")))))) -> 61-90 Days | U45: =IF(C45="","",IF(C45>0,IF(S45<30,"Normal",IF(S45<60,"Especially Mentioned",IF(S45<90,"Substandard",IF(S45<=180,"Doubtful",IF(S45>180,"Loss","0"))))),"Not Applicable")) -> Not Applicable
A46: 2026/08/06 | B46: 2026/08/06 | C46: 0 | D46: 1277.5 | E46: 229ZEXA2621801JP | F46: 2621805053513000 | H46: Outgoing Funds Transfer 06 AUG 26 02.51.56.170208 PM OBDX from MONSOON LTD to Matemwe Bungalows Zaswi Ltd 8000284. Remark: Commission July | S46: =IF(A46="","",A$5-A46) -> 81 | T46: =IF(S46="","",IF(S46<4,"0-3 Days",IF(S46<31,"4-30 Days",IF(S46<61,"31-60 Days",IF(S46<=90,"61-90 Days",IF(S46>90,"Above 90 Days","0")))))) -> 61-90 Days | U46: =IF(C46="","",IF(C46>0,IF(S46<30,"Normal",IF(S46<60,"Especially Mentioned",IF(S46<90,"Substandard",IF(S46<=180,"Doubtful",IF(S46>180,"Loss","0"))))),"Not Applicable")) -> Not Applicable
A47: 2026/08/06 | B47: 2026/08/06 | C47: 0 | D47: 4350 | E47: 417ZEXA262180009 | F47: 2621808040542000 | H47: Outgoing Funds Transfer 06 AUG 26 11.15.45.539528 AM OBDX from SHAIMAK COMPANY LIMITED to SHAIMAK COMPANY LIMITED 10121724354. Remark: FROM NMB | S47: =IF(A47="","",A$5-A47) -> 81 | T47: =IF(S47="","",IF(S47<4,"0-3 Days",IF(S47<31,"4-30 Days",IF(S47<61,"31-60 Days",IF(S47<=90,"61-90 Days",IF(S47>90,"Above 90 Days","0")))))) -> 61-90 Days | U47: =IF(C47="","",IF(C47>0,IF(S47<30,"Normal",IF(S47<60,"Especially Mentioned",IF(S47<90,"Substandard",IF(S47<=180,"Doubtful",IF(S47>180,"Loss","0"))))),"Not Applicable")) -> Not Applicable
A48: 2026/08/06 | B48: 2026/08/06 | C48: 0 | D48: 208 | E48: 226ZEXA2621800S6 | F48: 2621813035932000 | H48: Outgoing Funds Transfer 06 AUG 26 09.58.55.316871 AM OBDX from BTD SAFARI LIMITED to AMREF FLYING DOCTORS LIMITED 0018013010. Remark: FLYING DOCTORS | S48: =IF(A48="","",A$5-A48) -> 81 | T48: =IF(S48="","",IF(S48<4,"0-3 Days",IF(S48<31,"4-30 Days",IF(S48<61,"31-60 Days",IF(S48<=90,"61-90 Days",IF(S48>90,"Above 90 Days","0")))))) -> 61-90 Days | U48: =IF(C48="","",IF(C48>0,IF(S48<30,"Normal",IF(S48<60,"Especially Mentioned",IF(S48<90,"Substandard",IF(S48<=180,"Doubtful",IF(S48>180,"Loss","0"))))),"Not Applicable")) -> Not Applicable
A49: 2026/08/06 | B49: 2026/08/06 | C49: 0 | D49: 300 | E49: 435ZEXA26218000G | F49: 2621802049679000 | H49: Outgoing Funds Transfer 06 AUG 26 01.48.02.361130 PM OBDX from WEST WILD LIMITED to Conserve Safari Asset Management Limited 450428000065. Remark: | S49: =IF(A49="","",A$5-A49) -> 81 | T49: =IF(S49="","",IF(S49<4,"0-3 Days",IF(S49<31,"4-30 Days",IF(S49<61,"31-60 Days",IF(S49<=90,"61-90 Days",IF(S49>90,"Above 90 Days","0")))))) -> 61-90 Days | U49: =IF(C49="","",IF(C49>0,IF(S49<30,"Normal",IF(S49<60,"Especially Mentioned",IF(S49<90,"Substandard",IF(S49<=180,"Doubtful",IF(S49>180,"Loss","0"))))),"Not Applicable")) -> Not Applicable
A50: 2026/08/06 | B50: 2026/08/06 | C50: 13334 | D50: 0 | E50: 101cbs3262180741 | H50: 06 AUG 26 02.27.01.702282 PM => 10109000006 BOT CLEARING USD via FLEXCUBE BEING INCOMING TISS MANUALLY POSTED REF NO TZ2OL26080602571 | S50: =IF(A50="","",A$5-A50) -> 81 | T50: =IF(S50="","",IF(S50<4,"0-3 Days",IF(S50<31,"4-30 Days",IF(S50<61,"31-60 Days",IF(S50<=90,"61-90 Days",IF(S50>90,"Above 90 Days","0")))))) -> 61-90 Days | U50: =IF(C50="","",IF(C50>0,IF(S50<30,"Normal",IF(S50<60,"Especially Mentioned",IF(S50<90,"Substandard",IF(S50<=180,"Doubtful",IF(S50>180,"Loss","0"))))),"Not Applicable")) -> Substandard
A51: 2026/08/06 | B51: 2026/08/06 | C51: 0 | D51: 11700 | E51: 225ZEXA2621800S3 | F51: 2621815038234000 | H51: Outgoing Funds Transfer 06 AUG 26 10.37.17.358833 AM OBDX from SAVANNAH TRADING LIMITED to DS STEEL AND GENERAL SUPPLIES 10386005066. Remark: | S51: =IF(A51="","",A$5-A51) -> 81 | T51: =IF(S51="","",IF(S51<4,"0-3 Days",IF(S51<31,"4-30 Days",IF(S51<61,"31-60 Days",IF(S51<=90,"61-90 Days",IF(S51>90,"Above 90 Days","0")))))) -> 61-90 Days | U51: =IF(C51="","",IF(C51>0,IF(S51<30,"Normal",IF(S51<60,"Especially Mentioned",IF(S51<90,"Substandard",IF(S51<=180,"Doubtful",IF(S51>180,"Loss","0"))))),"Not Applicable")) -> Not Applicable
A52: 2026/08/06 | B52: 2026/08/06 | C52: 0 | D52: 11200 | E52: 201ZEXA2621801NJ | F52: 2621812065432001 | H52: Outgoing Funds Transfer 06 AUG 26 06.10.35.768412 PM OBDX from TOPMAX TANZANIA LIMITED to TRY AGAIN LOGISTICS LTD 0250755639800. Remark: TRANSPORT COST ALPHA727 NIKA 11 | S52: =IF(A52="","",A$5-A52) -> 81 | T52: =IF(S52="","",IF(S52<4,"0-3 Days",IF(S52<31,"4-30 Days",IF(S52<61,"31-60 Days",IF(S52<=90,"61-90 Days",IF(S52>90,"Above 90 Days","0")))))) -> 61-90 Days | U52: =IF(C52="","",IF(C52>0,IF(S52<30,"Normal",IF(S52<60,"Especially Mentioned",IF(S52<90,"Substandard",IF(S52<=180,"Doubtful",IF(S52>180,"Loss","0"))))),"Not Applicable")) -> Not Applicable
A53: 2026/08/06 | B53: 2026/08/06 | C53: 840 | D53: 0 | E53: 428ZEXA26218008J | F53: TAPBTZTZ20260806135428362 | H53: Incoming Funds Transfer on 06 AUG 26 01.55.06.600248 PM from AMSHAR SERENGETI ADVENTURE COMPANY LIMITED at . Remarks: Payment for DEMI WATSON | S53: =IF(A53="","",A$5-A53) -> 81 | T53: =IF(S53="","",IF(S53<4,"0-3 Days",IF(S53<31,"4-30 Days",IF(S53<61,"31-60 Days",IF(S53<=90,"61-90 Days",IF(S53>90,"Above 90 Days","0")))))) -> 61-90 Days | U53: =IF(C53="","",IF(C53>0,IF(S53<30,"Normal",IF(S53<60,"Especially Mentioned",IF(S53<90,"Substandard",IF(S53<=180,"Doubtful",IF(S53>180,"Loss","0"))))),"Not Applicable")) -> Substandard
A54: 2026/08/06 | B54: 2026/08/06 | C54: 0 | D54: 240 | E54: 428ZEXA262180068 | F54: 2621805047184000 | H54: Outgoing Funds Transfer 06 AUG 26 01.06.27.315254 PM OBDX from KARANI EXPEDITIONS ( TZ ) LIMITED to WERUWERU RIVER LODGE LIMITED 017105004001. Remark: Salma harignordoguy | S54: =IF(A54="","",A$5-A54) -> 81 | T54: =IF(S54="","",IF(S54<4,"0-3 Days",IF(S54<31,"4-30 Days",IF(S54<61,"31-60 Days",IF(S54<=90,"61-90 Days",IF(S54>90,"Above 90 Days","0")))))) -> 61-90 Days | U54: =IF(C54="","",IF(C54>0,IF(S54<30,"Normal",IF(S54<60,"Especially Mentioned",IF(S54<90,"Substandard",IF(S54<=180,"Doubtful",IF(S54>180,"Loss","0"))))),"Not Applicable")) -> Not Applicable
A55: 2026/08/06 | B55: 2026/08/06 | C55: 0 | D55: 500 | E55: 428ZEXA2621800U9 | F55: 2621811044672000 | H55: Outgoing Funds Transfer 06 AUG 26 12.24.35.881534 PM OBDX from TANZANIA CHOICE SAFARIS LTD to SERENGETI SIMBA TANZANIA LTD 0070012149. Remark: 0227 THOMPSON DEPOSIT WB36007 | S55: =IF(A55="","",A$5-A55) -> 81 | T55: =IF(S55="","",IF(S55<4,"0-3 Days",IF(S55<31,"4-30 Days",IF(S55<61,"31-60 Days",IF(S55<=90,"61-90 Days",IF(S55>90,"Above 90 Days","0")))))) -> 61-90 Days | U55: =IF(C55="","",IF(C55>0,IF(S55<30,"Normal",IF(S55<60,"Especially Mentioned",IF(S55<90,"Substandard",IF(S55<=180,"Doubtful",IF(S55>180,"Loss","0"))))),"Not Applicable")) -> Not Applicable
A56: 2026/08/06 | B56: 2026/08/06 | C56: 500 | D56: 0 | E56: 101cbs3262180674 | H56: 06 AUG 26 02.27.01.160585 PM => 10109000006 BOT CLEARING USD via FLEXCUBE BEING INCOMING TISS MANUALLY POSTED REF NO 1.78558E 13 | S56: =IF(A56="","",A$5-A56) -> 81 | T56: =IF(S56="","",IF(S56<4,"0-3 Days",IF(S56<31,"4-30 Days",IF(S56<61,"31-60 Days",IF(S56<=90,"61-90 Days",IF(S56>90,"Above 90 Days","0")))))) -> 61-90 Days | U56: =IF(C56="","",IF(C56>0,IF(S56<30,"Normal",IF(S56<60,"Especially Mentioned",IF(S56<90,"Substandard",IF(S56<=180,"Doubtful",IF(S56>180,"Loss","0"))))),"Not Applicable")) -> Substandard
A57: 2026/08/06 | B57: 2026/08/06 | C57: 600 | D57: 0 | E57: 101cbs3262180717 | H57: 06 AUG 26 02.27.01.525773 PM => 10109000006 BOT CLEARING USD via FLEXCUBE BEING INCOMING TISS MANUALLY POSTED REF NO TZAAO21326HB325 | S57: =IF(A57="","",A$5-A57) -> 81 | T57: =IF(S57="","",IF(S57<4,"0-3 Days",IF(S57<31,"4-30 Days",IF(S57<61,"31-60 Days",IF(S57<=90,"61-90 Days",IF(S57>90,"Above 90 Days","0")))))) -> 61-90 Days | U57: =IF(C57="","",IF(C57>0,IF(S57<30,"Normal",IF(S57<60,"Especially Mentioned",IF(S57<90,"Substandard",IF(S57<=180,"Doubtful",IF(S57>180,"Loss","0"))))),"Not Applicable")) -> Substandard
A58: 2026/08/06 | B58: 2026/08/06 | C58: 0 | D58: 1119 | E58: 435ZEXA26218000P | F58: 2621822055690000 | H58: Outgoing Funds Transfer 06 AUG 26 03.28.18.950284 PM OBDX from WEST WILD LIMITED to UNTAMED MIGRATION CAMPS 0309786001. Remark: | S58: =IF(A58="","",A$5-A58) -> 81 | T58: =IF(S58="","",IF(S58<4,"0-3 Days",IF(S58<31,"4-30 Days",IF(S58<61,"31-60 Days",IF(S58<=90,"61-90 Days",IF(S58>90,"Above 90 Days","0")))))) -> 61-90 Days | U58: =IF(C58="","",IF(C58>0,IF(S58<30,"Normal",IF(S58<60,"Especially Mentioned",IF(S58<90,"Substandard",IF(S58<=180,"Doubtful",IF(S58>180,"Loss","0"))))),"Not Applicable")) -> Not Applicable
A59: 2026/08/06 | B59: 2026/08/06 | C59: 70000 | D59: 0 | E59: 101cbs3262180677 | H59: 06 AUG 26 02.27.01.191741 PM => 10109000006 BOT CLEARING USD via FLEXCUBE BEING INCOMING TISS MANUALLY POSTED REF NO TZ1OL2608030255Y | S59: =IF(A59="","",A$5-A59) -> 81 | T59: =IF(S59="","",IF(S59<4,"0-3 Days",IF(S59<31,"4-30 Days",IF(S59<61,"31-60 Days",IF(S59<=90,"61-90 Days",IF(S59>90,"Above 90 Days","0")))))) -> 61-90 Days | U59: =IF(C59="","",IF(C59>0,IF(S59<30,"Normal",IF(S59<60,"Especially Mentioned",IF(S59<90,"Substandard",IF(S59<=180,"Doubtful",IF(S59>180,"Loss","0"))))),"Not Applicable")) -> Substandard
A60: 2026/08/06 | B60: 2026/08/06 | C60: 0 | D60: 38.14 | E60: 243ZEXA2621801JO | F60: 2621823059458000 | H60: Outgoing Funds Transfer 06 AUG 26 04.31.01.636319 PM OBDX from SPRINT CARGO LIMITED to Chinese Tanzanian Joint Shipping 0370000152. Remark: | S60: =IF(A60="","",A$5-A60) -> 81 | T60: =IF(S60="","",IF(S60<4,"0-3 Days",IF(S60<31,"4-30 Days",IF(S60<61,"31-60 Days",IF(S60<=90,"61-90 Days",IF(S60>90,"Above 90 Days","0")))))) -> 61-90 Days | U60: =IF(C60="","",IF(C60>0,IF(S60<30,"Normal",IF(S60<60,"Especially Mentioned",IF(S60<90,"Substandard",IF(S60<=180,"Doubtful",IF(S60>180,"Loss","0"))))),"Not Applicable")) -> Not Applicable
A61: 2026/08/06 | B61: 2026/08/06 | C61: 1294.7 | D61: 0 | E61: 101cbs3262180685 | H61: 06 AUG 26 02.27.01.264786 PM => 10109000006 BOT CLEARING USD via FLEXCUBE BEING INCOMING TISS MANUALLY POSTED REF NO 005COUS030826002 | S61: =IF(A61="","",A$5-A61) -> 81 | T61: =IF(S61="","",IF(S61<4,"0-3 Days",IF(S61<31,"4-30 Days",IF(S61<61,"31-60 Days",IF(S61<=90,"61-90 Days",IF(S61>90,"Above 90 Days","0")))))) -> 61-90 Days | U61: =IF(C61="","",IF(C61>0,IF(S61<30,"Normal",IF(S61<60,"Especially Mentioned",IF(S61<90,"Substandard",IF(S61<=180,"Doubtful",IF(S61>180,"Loss","0"))))),"Not Applicable")) -> Substandard
A62: 2026/08/06 | B62: 2026/08/06 | C62: 0 | D62: 1333.2 | E62: 408ZEXA26218001A | F62: CMD1225EA42915 | H62: Outgoing Funds Transfer 06 AUG 26 09.23.26.999358 AM OBDX from SERENGETI CLARITY to KON TIKI AFRICA CO LTD 025C73139850. Remark: Michelle Ethan x4 | S62: =IF(A62="","",A$5-A62) -> 81 | T62: =IF(S62="","",IF(S62<4,"0-3 Days",IF(S62<31,"4-30 Days",IF(S62<61,"31-60 Days",IF(S62<=90,"61-90 Days",IF(S62>90,"Above 90 Days","0")))))) -> 61-90 Days | U62: =IF(C62="","",IF(C62>0,IF(S62<30,"Normal",IF(S62<60,"Especially Mentioned",IF(S62<90,"Substandard",IF(S62<=180,"Doubtful",IF(S62>180,"Loss","0"))))),"Not Applicable")) -> Not Applicable
A63: 2026/08/06 | B63: 2026/08/06 | C63: 27300 | D63: 0 | E63: 101cbs3262180670 | H63: 06 AUG 26 02.27.01.115303 PM => 10109000006 BOT CLEARING USD via FLEXCUBE BEING INCOMING TISS MANUALLY POSTED REF NO 011COUS030826008 | S63: =IF(A63="","",A$5-A63) -> 81 | T63: =IF(S63="","",IF(S63<4,"0-3 Days",IF(S63<31,"4-30 Days",IF(S63<61,"31-60 Days",IF(S63<=90,"61-90 Days",IF(S63>90,"Above 90 Days","0")))))) -> 61-90 Days | U63: =IF(C63="","",IF(C63>0,IF(S63<30,"Normal",IF(S63<60,"Especially Mentioned",IF(S63<90,"Substandard",IF(S63<=180,"Doubtful",IF(S63>180,"Loss","0"))))),"Not Applicable")) -> Substandard
A64: 2026/08/06 | B64: 2026/08/06 | C64: 0 | D64: 491 | E64: 403ZEXA2621800RV | F64: 2621810028147000 | H64: Outgoing Funds Transfer 06 AUG 26 07.49.11.302016 AM OBDX from MAKASA LIMITED to ONE BIKE TANZANIA LIMITED 30034666003. Remark: | S64: =IF(A64="","",A$5-A64) -> 81 | T64: =IF(S64="","",IF(S64<4,"0-3 Days",IF(S64<31,"4-30 Days",IF(S64<61,"31-60 Days",IF(S64<=90,"61-90 Days",IF(S64>90,"Above 90 Days","0")))))) -> 61-90 Days | U64: =IF(C64="","",IF(C64>0,IF(S64<30,"Normal",IF(S64<60,"Especially Mentioned",IF(S64<90,"Substandard",IF(S64<=180,"Doubtful",IF(S64>180,"Loss","0"))))),"Not Applicable")) -> Not Applicable
A65: 2026/08/10 | B65: 2026/08/07 | C65: 0 | D65: -1000 | E65: 239ZEXA262190017 | H65: Outgoing Funds Transfer 10 AUG 26 12.23.04.854414 PM FLEXCUBE from KARAN PETROLEUM LIMITED to Sagar Paudel 5342109001. Remark: Salary Advance | S65: =IF(A65="","",A$5-A65) -> 77 | T65: =IF(S65="","",IF(S65<4,"0-3 Days",IF(S65<31,"4-30 Days",IF(S65<61,"31-60 Days",IF(S65<=90,"61-90 Days",IF(S65>90,"Above 90 Days","0")))))) -> 61-90 Days | U65: =IF(C65="","",IF(C65>0,IF(S65<30,"Normal",IF(S65<60,"Especially Mentioned",IF(S65<90,"Substandard",IF(S65<=180,"Doubtful",IF(S65>180,"Loss","0"))))),"Not Applicable")) -> Not Applicable
A66: 2026/08/07 | B66: 2026/08/07 | C66: 680 | D66: 0 | E66: 101ref2262190682 | H66: 07 AUG 26 11.30.58.079890 AM => 10109000006 BOT CLEARING USD via FLEXCUBE INCOMING FUND TRANSFER REF NO17858303616637 | S66: =IF(A66="","",A$5-A66) -> 80 | T66: =IF(S66="","",IF(S66<4,"0-3 Days",IF(S66<31,"4-30 Days",IF(S66<61,"31-60 Days",IF(S66<=90,"61-90 Days",IF(S66>90,"Above 90 Days","0")))))) -> 61-90 Days | U66: =IF(C66="","",IF(C66>0,IF(S66<30,"Normal",IF(S66<60,"Especially Mentioned",IF(S66<90,"Substandard",IF(S66<=180,"Doubtful",IF(S66>180,"Loss","0"))))),"Not Applicable")) -> Substandard
A67: 2026/08/07 | B67: 2026/08/07 | C67: 0 | D67: 300 | E67: 421ZEXA26219000I | F67: CMD213166A88D3 | H67: Outgoing Funds Transfer 07 AUG 26 10.58.01.731922 AM OBDX from MAGIC OF WILD LIMITED to SERVAL WILDLIFE LIMITED 025066718110. Remark: day trip shyma | S67: =IF(A67="","",A$5-A67) -> 80 | T67: =IF(S67="","",IF(S67<4,"0-3 Days",IF(S67<31,"4-30 Days",IF(S67<61,"31-60 Days",IF(S67<=90,"61-90 Days",IF(S67>90,"Above 90 Days","0")))))) -> 61-90 Days | U67: =IF(C67="","",IF(C67>0,IF(S67<30,"Normal",IF(S67<60,"Especially Mentioned",IF(S67<90,"Substandard",IF(S67<=180,"Doubtful",IF(S67>180,"Loss","0"))))),"Not Applicable")) -> Not Applicable
A68: 2026/08/07 | B68: 2026/08/07 | C68: 1200 | D68: 0 | E68: 101ref2262190366 | H68: 07 AUG 26 11.30.57.048937 AM => 10109000006 BOT CLEARING USD via FLEXCUBE INCOMING FUND TRANSFER REF NO17854121336867 | S68: =IF(A68="","",A$5-A68) -> 80 | T68: =IF(S68="","",IF(S68<4,"0-3 Days",IF(S68<31,"4-30 Days",IF(S68<61,"31-60 Days",IF(S68<=90,"61-90 Days",IF(S68>90,"Above 90 Days","0")))))) -> 61-90 Days | U68: =IF(C68="","",IF(C68>0,IF(S68<30,"Normal",IF(S68<60,"Especially Mentioned",IF(S68<90,"Substandard",IF(S68<=180,"Doubtful",IF(S68>180,"Loss","0"))))),"Not Applicable")) -> Substandard
A69: 2026/08/07 | B69: 2026/08/07 | C69: 0 | D69: 725 | E69: 428ZEXA26219001M | F69: ACTZ5023563752 | H69: Outgoing Funds Transfer 07 AUG 26 10.37.14.557559 AM OBDX from SAKATA SAFARIS AFRICA CO LTD to Zawadi Luxury Camps Limited 7036385522. Remark: FASANA X5 | S69: =IF(A69="","",A$5-A69) -> 80 | T69: =IF(S69="","",IF(S69<4,"0-3 Days",IF(S69<31,"4-30 Days",IF(S69<61,"31-60 Days",IF(S69<=90,"61-90 Days",IF(S69>90,"Above 90 Days","0")))))) -> 61-90 Days | U69: =IF(C69="","",IF(C69>0,IF(S69<30,"Normal",IF(S69<60,"Especially Mentioned",IF(S69<90,"Substandard",IF(S69<=180,"Doubtful",IF(S69>180,"Loss","0"))))),"Not Applicable")) -> Not Applicable
A70: 2026/08/07 | B70: 2026/08/07 | C70: 0 | D70: 2100 | E70: 428ZEXA262190031 | F70: CM224D36DBFC71 | H70: Outgoing Funds Transfer 07 AUG 26 12.13.21.593005 PM OBDX from AFRICA JOY TOURS AND SAFARIS LTD to MOTTO COTTAGES LTD 02C595582500. Remark: | S70: =IF(A70="","",A$5-A70) -> 80 | T70: =IF(S70="","",IF(S70<4,"0-3 Days",IF(S70<31,"4-30 Days",IF(S70<61,"31-60 Days",IF(S70<=90,"61-90 Days",IF(S70>90,"Above 90 Days","0")))))) -> 61-90 Days | U70: =IF(C70="","",IF(C70>0,IF(S70<30,"Normal",IF(S70<60,"Especially Mentioned",IF(S70<90,"Substandard",IF(S70<=180,"Doubtful",IF(S70>180,"Loss","0"))))),"Not Applicable")) -> Not Applicable
A71: 2026/08/07 | B71: 2026/08/07 | C71: 1920 | D71: 0 | E71: 101ref2262190686 | H71: 07 AUG 26 11.30.58.101482 AM => 10109000006 BOT CLEARING USD via FLEXCUBE INCOMING FUND TRANSFER REF NO17858305330460 | S71: =IF(A71="","",A$5-A71) -> 80 | T71: =IF(S71="","",IF(S71<4,"0-3 Days",IF(S71<31,"4-30 Days",IF(S71<61,"31-60 Days",IF(S71<=90,"61-90 Days",IF(S71>90,"Above 90 Days","0")))))) -> 61-90 Days | U71: =IF(C71="","",IF(C71>0,IF(S71<30,"Normal",IF(S71<60,"Especially Mentioned",IF(S71<90,"Substandard",IF(S71<=180,"Doubtful",IF(S71>180,"Loss","0"))))),"Not Applicable")) -> Substandard
A72: 2026/08/07 | B72: 2026/08/07 | C72: 0 | D72: 430 | E72: 229ZEXA2621900SI | F72: RETN08070134968 | H72: Outgoing Funds Transfer 07 AUG 26 12.06.39.553618 PM OBDX from TAKE A TRIP TRAVEL AND TOURS LIMITED to IBRAHIM MASHAKA KASSARA 300711156797. Remark: MNEMBA TOUR PAYMENT | S72: =IF(A72="","",A$5-A72) -> 80 | T72: =IF(S72="","",IF(S72<4,"0-3 Days",IF(S72<31,"4-30 Days",IF(S72<61,"31-60 Days",IF(S72<=90,"61-90 Days",IF(S72>90,"Above 90 Days","0")))))) -> 61-90 Days | U72: =IF(C72="","",IF(C72>0,IF(S72<30,"Normal",IF(S72<60,"Especially Mentioned",IF(S72<90,"Substandard",IF(S72<=180,"Doubtful",IF(S72>180,"Loss","0"))))),"Not Applicable")) -> Not Applicable
A73: 2026/08/07 | B73: 2026/08/07 | C73: 0 | D73: 3553.2 | E73: 428ZEXA2621900SP | F73: CTZ00026219NGL2 | H73: Outgoing Funds Transfer 07 AUG 26 10.10.32.280383 AM OBDX from GET TOGETHER ADVENTURES LTD to The Royal Zanzibar Beach Resort LTD 0880824002. Remark: | S73: =IF(A73="","",A$5-A73) -> 80 | T73: =IF(S73="","",IF(S73<4,"0-3 Days",IF(S73<31,"4-30 Days",IF(S73<61,"31-60 Days",IF(S73<=90,"61-90 Days",IF(S73>90,"Above 90 Days","0")))))) -> 61-90 Days | U73: =IF(C73="","",IF(C73>0,IF(S73<30,"Normal",IF(S73<60,"Especially Mentioned",IF(S73<90,"Substandard",IF(S73<=180,"Doubtful",IF(S73>180,"Loss","0"))))),"Not Applicable")) -> Not Applicable
A74: 2026/08/07 | B74: 2026/08/07 | C74: 70 | D74: 0 | E74: 101ref2262190689 | H74: 07 AUG 26 11.31.11.205799 AM => 10109000006 BOT CLEARING USD via FLEXCUBE INCOMING FUND TRANSFER REF NO17858315711954 | S74: =IF(A74="","",A$5-A74) -> 80 | T74: =IF(S74="","",IF(S74<4,"0-3 Days",IF(S74<31,"4-30 Days",IF(S74<61,"31-60 Days",IF(S74<=90,"61-90 Days",IF(S74>90,"Above 90 Days","0")))))) -> 61-90 Days | U74: =IF(C74="","",IF(C74>0,IF(S74<30,"Normal",IF(S74<60,"Especially Mentioned",IF(S74<90,"Substandard",IF(S74<=180,"Doubtful",IF(S74>180,"Loss","0"))))),"Not Applicable")) -> Substandard
A75: 2026/08/07 | B75: 2026/08/07 | C75: 0 | D75: 365 | E75: 239ZEXA2621900WR | F75: CM255A7401484B | H75: Outgoing Funds Transfer 07 AUG 26 05.13.59.298426 PM OBDX from JAKAYA MRISHO KIKWETE FOUNDATION to Medard Edward Ngaiza 01J248818000. Remark: pv 3305 | S75: =IF(A75="","",A$5-A75) -> 80 | T75: =IF(S75="","",IF(S75<4,"0-3 Days",IF(S75<31,"4-30 Days",IF(S75<61,"31-60 Days",IF(S75<=90,"61-90 Days",IF(S75>90,"Above 90 Days","0")))))) -> 61-90 Days | U75: =IF(C75="","",IF(C75>0,IF(S75<30,"Normal",IF(S75<60,"Especially Mentioned",IF(S75<90,"Substandard",IF(S75<=180,"Doubtful",IF(S75>180,"Loss","0"))))),"Not Applicable")) -> Not Applicable
A76: 2026/08/07 | B76: 2026/08/07 | C76: 170 | D76: 0 | E76: 101ref2262190669 | H76: 07 AUG 26 11.31.02.662012 AM => 10109000006 BOT CLEARING USD via FLEXCUBE INCOMING FUND TRANSFER REF NO17858299583615 | S76: =IF(A76="","",A$5-A76) -> 80 | T76: =IF(S76="","",IF(S76<4,"0-3 Days",IF(S76<31,"4-30 Days",IF(S76<61,"31-60 Days",IF(S76<=90,"61-90 Days",IF(S76>90,"Above 90 Days","0")))))) -> 61-90 Days | U76: =IF(C76="","",IF(C76>0,IF(S76<30,"Normal",IF(S76<60,"Especially Mentioned",IF(S76<90,"Substandard",IF(S76<=180,"Doubtful",IF(S76>180,"Loss","0"))))),"Not Applicable")) -> Substandard
A77: 2026/08/07 | B77: 2026/08/07 | C77: 0 | D77: 500 | E77: 239ZEXA2621900WS | F77: CM9C23383CD39B | H77: Outgoing Funds Transfer 07 AUG 26 05.14.00.557393 PM OBDX from JAKAYA MRISHO KIKWETE FOUNDATION to Merdad Edward Ngaiza 01J248818000. Remark: pv 3404 | S77: =IF(A77="","",A$5-A77) -> 80 | T77: =IF(S77="","",IF(S77<4,"0-3 Days",IF(S77<31,"4-30 Days",IF(S77<61,"31-60 Days",IF(S77<=90,"61-90 Days",IF(S77>90,"Above 90 Days","0")))))) -> 61-90 Days | U77: =IF(C77="","",IF(C77>0,IF(S77<30,"Normal",IF(S77<60,"Especially Mentioned",IF(S77<90,"Substandard",IF(S77<=180,"Doubtful",IF(S77>180,"Loss","0"))))),"Not Applicable")) -> Not Applicable
A78: 2026/08/07 | B78: 2026/08/07 | C78: 110 | D78: 0 | E78: 101ref2262190690 | H78: 07 AUG 26 11.31.02.707801 AM => 10109000006 BOT CLEARING USD via FLEXCUBE INCOMING FUND TRANSFER REF NOTZAAO21626HQA5X | S78: =IF(A78="","",A$5-A78) -> 80 | T78: =IF(S78="","",IF(S78<4,"0-3 Days",IF(S78<31,"4-30 Days",IF(S78<61,"31-60 Days",IF(S78<=90,"61-90 Days",IF(S78>90,"Above 90 Days","0")))))) -> 61-90 Days | U78: =IF(C78="","",IF(C78>0,IF(S78<30,"Normal",IF(S78<60,"Especially Mentioned",IF(S78<90,"Substandard",IF(S78<=180,"Doubtful",IF(S78>180,"Loss","0"))))),"Not Applicable")) -> Substandard
A79: 2026/08/07 | B79: 2026/08/07 | C79: 290 | D79: 0 | E79: 101ref2262190679 | H79: 07 AUG 26 11.30.58.057959 AM => 10109000006 BOT CLEARING USD via FLEXCUBE INCOMING FUND TRANSFER REF NO17858300021427 | S79: =IF(A79="","",A$5-A79) -> 80 | T79: =IF(S79="","",IF(S79<4,"0-3 Days",IF(S79<31,"4-30 Days",IF(S79<61,"31-60 Days",IF(S79<=90,"61-90 Days",IF(S79>90,"Above 90 Days","0")))))) -> 61-90 Days | U79: =IF(C79="","",IF(C79>0,IF(S79<30,"Normal",IF(S79<60,"Especially Mentioned",IF(S79<90,"Substandard",IF(S79<=180,"Doubtful",IF(S79>180,"Loss","0"))))),"Not Applicable")) -> Substandard
A80: 2026/08/07 | B80: 2026/08/07 | C80: 0 | D80: 50000 | E80: 421ZEXA262190005 | F80: ACTZ9696705778 | H80: Outgoing Funds Transfer 07 AUG 26 08.38.35.468310 AM OBDX from OLASITI VENTURES LIMITED to ACCESS BANK TANZANIA LIMITED 1010203125. Remark: | S80: =IF(A80="","",A$5-A80) -> 80 | T80: =IF(S80="","",IF(S80<4,"0-3 Days",IF(S80<31,"4-30 Days",IF(S80<61,"31-60 Days",IF(S80<=90,"61-90 Days",IF(S80>90,"Above 90 Days","0")))))) -> 61-90 Days | U80: =IF(C80="","",IF(C80>0,IF(S80<30,"Normal",IF(S80<60,"Especially Mentioned",IF(S80<90,"Substandard",IF(S80<=180,"Doubtful",IF(S80>180,"Loss","0"))))),"Not Applicable")) -> Not Applicable
A81: 2026/08/08 | B81: 2026/08/08 | C81: 0 | D81: 35815.36 | E81: 225SBRN262200001 | F81: CM7DB8751FFC0D | H81: Outgoing Funds Transfer 08 AUG 26 11.00.22.119955 AM SYBRIN from TANZANIA TOOKU GARMENTS CO. LTD to PMM ESTATE 2001 LIMITED 2J1020582600. Remark: /TRANSFER FOR AGENT | S81: =IF(A81="","",A$5-A81) -> 79 | T81: =IF(S81="","",IF(S81<4,"0-3 Days",IF(S81<31,"4-30 Days",IF(S81<61,"31-60 Days",IF(S81<=90,"61-90 Days",IF(S81>90,"Above 90 Days","0")))))) -> 61-90 Days | U81: =IF(C81="","",IF(C81>0,IF(S81<30,"Normal",IF(S81<60,"Especially Mentioned",IF(S81<90,"Substandard",IF(S81<=180,"Doubtful",IF(S81>180,"Loss","0"))))),"Not Applicable")) -> Not Applicable
A82: 2026/08/09 | B82: 2026/08/09 | C82: 3434.3 | D82: 0 | E82: 101inc5262210304 | H82: 09 AUG 26 02.59.48.472323 PM => 10109000006 BOT CLEARING USD via FLEXCUBE 014TOUS040826007 | S82: =IF(A82="","",A$5-A82) -> 78 | T82: =IF(S82="","",IF(S82<4,"0-3 Days",IF(S82<31,"4-30 Days",IF(S82<61,"31-60 Days",IF(S82<=90,"61-90 Days",IF(S82>90,"Above 90 Days","0")))))) -> 61-90 Days | U82: =IF(C82="","",IF(C82>0,IF(S82<30,"Normal",IF(S82<60,"Especially Mentioned",IF(S82<90,"Substandard",IF(S82<=180,"Doubtful",IF(S82>180,"Loss","0"))))),"Not Applicable")) -> Substandard
A83: 2026/08/09 | B83: 2026/08/09 | C83: 30000 | D83: 0 | E83: 101inc5262210257 | H83: 09 AUG 26 02.59.48.169546 PM => 10109000006 BOT CLEARING USD via FLEXCUBE HZ1JUT0GHVB21B8C | S83: =IF(A83="","",A$5-A83) -> 78 | T83: =IF(S83="","",IF(S83<4,"0-3 Days",IF(S83<31,"4-30 Days",IF(S83<61,"31-60 Days",IF(S83<=90,"61-90 Days",IF(S83>90,"Above 90 Days","0")))))) -> 61-90 Days | U83: =IF(C83="","",IF(C83>0,IF(S83<30,"Normal",IF(S83<60,"Especially Mentioned",IF(S83<90,"Substandard",IF(S83<=180,"Doubtful",IF(S83>180,"Loss","0"))))),"Not Applicable")) -> Substandard
A84: 2026/08/09 | B84: 2026/08/09 | C84: 50000 | D84: 0 | E84: 101inc5262210252 | H84: 09 AUG 26 02.59.48.138827 PM => 10109000006 BOT CLEARING USD via FLEXCUBE CMRTG26217000847 | S84: =IF(A84="","",A$5-A84) -> 78 | T84: =IF(S84="","",IF(S84<4,"0-3 Days",IF(S84<31,"4-30 Days",IF(S84<61,"31-60 Days",IF(S84<=90,"61-90 Days",IF(S84>90,"Above 90 Days","0")))))) -> 61-90 Days | U84: =IF(C84="","",IF(C84>0,IF(S84<30,"Normal",IF(S84<60,"Especially Mentioned",IF(S84<90,"Substandard",IF(S84<=180,"Doubtful",IF(S84>180,"Loss","0"))))),"Not Applicable")) -> Substandard
A85: 2026/08/10 | B85: 2026/08/10 | C85: 0 | D85: 50 | E85: 408ZEXA26222013Z | F85: CM43209BCAC1B6 | H85: Outgoing Funds Transfer 10 AUG 26 05.19.26.001392 PM OBDX from MOUNT MERU MILLERS LTD to Nyota Tanzania Limited 100269056. Remark: | S85: =IF(A85="","",A$5-A85) -> 77 | T85: =IF(S85="","",IF(S85<4,"0-3 Days",IF(S85<31,"4-30 Days",IF(S85<61,"31-60 Days",IF(S85<=90,"61-90 Days",IF(S85>90,"Above 90 Days","0")))))) -> 61-90 Days | U85: =IF(C85="","",IF(C85>0,IF(S85<30,"Normal",IF(S85<60,"Especially Mentioned",IF(S85<90,"Substandard",IF(S85<=180,"Doubtful",IF(S85>180,"Loss","0"))))),"Not Applicable")) -> Not Applicable
A86: 2026/08/10 | B86: 2026/08/10 | C86: 720169.65 | D86: 0 | E86: 101tane262220001 | H86: 10 AUG 26 09.03.22.214784 PM => 10109000006 BOT CLEARING USD via FLEXCUBE 223LC02233180501 | S86: =IF(A86="","",A$5-A86) -> 77 | T86: =IF(S86="","",IF(S86<4,"0-3 Days",IF(S86<31,"4-30 Days",IF(S86<61,"31-60 Days",IF(S86<=90,"61-90 Days",IF(S86>90,"Above 90 Days","0")))))) -> 61-90 Days | U86: =IF(C86="","",IF(C86>0,IF(S86<30,"Normal",IF(S86<60,"Especially Mentioned",IF(S86<90,"Substandard",IF(S86<=180,"Doubtful",IF(S86>180,"Loss","0"))))),"Not Applicable")) -> Substandard
A87: 2026/08/11 | B87: 2026/08/11 | C87: 0 | D87: 1774 | E87: 439SBRN262230002 | F87: GWX103374136368 | H87: Outgoing Funds Transfer 11 AUG 26 06.25.11.484563 PM SYBRIN from BINTI WA AFRIKA COLLECTION to SIMPLY CLASSIC LIMITED 00800796221211. Remark: /BEADED DOG COLLARS | S87: =IF(A87="","",A$5-A87) -> 76 | T87: =IF(S87="","",IF(S87<4,"0-3 Days",IF(S87<31,"4-30 Days",IF(S87<61,"31-60 Days",IF(S87<=90,"61-90 Days",IF(S87>90,"Above 90 Days","0")))))) -> 61-90 Days | U87: =IF(C87="","",IF(C87>0,IF(S87<30,"Normal",IF(S87<60,"Especially Mentioned",IF(S87<90,"Substandard",IF(S87<=180,"Doubtful",IF(S87>180,"Loss","0"))))),"Not Applicable")) -> Not Applicable
A88: 2026/08/11 | B88: 2026/08/11 | C88: 0.59 | D88: 0 | E88: 439SBRN262230002 | F88: GWX103374136368 | H88: VAT Payable on Comm and Fees 11 AUG 26 06.25.11.483314 PM SYBRIN from BINTI WA AFRIKA COLLECTION to SIMPLY CLASSIC LIMITED 00800796221211. Remark: /BEADED DOG COLLARS | S88: =IF(A88="","",A$5-A88) -> 76 | T88: =IF(S88="","",IF(S88<4,"0-3 Days",IF(S88<31,"4-30 Days",IF(S88<61,"31-60 Days",IF(S88<=90,"61-90 Days",IF(S88>90,"Above 90 Days","0")))))) -> 61-90 Days | U88: =IF(C88="","",IF(C88>0,IF(S88<30,"Normal",IF(S88<60,"Especially Mentioned",IF(S88<90,"Substandard",IF(S88<=180,"Doubtful",IF(S88>180,"Loss","0"))))),"Not Applicable")) -> Substandard
A89: 2026/08/11 | B89: 2026/08/11 | C89: 3.27 | D89: 0 | E89: 439SBRN262230002 | F89: GWX103374136368 | H89: Commission on Funds Transfer 11 AUG 26 06.25.11.480919 PM SYBRIN from BINTI WA AFRIKA COLLECTION to SIMPLY CLASSIC LIMITED 00800796221211. Remark: /BEADED DOG COLLARS | S89: =IF(A89="","",A$5-A89) -> 76 | T89: =IF(S89="","",IF(S89<4,"0-3 Days",IF(S89<31,"4-30 Days",IF(S89<61,"31-60 Days",IF(S89<=90,"61-90 Days",IF(S89>90,"Above 90 Days","0")))))) -> 61-90 Days | U89: =IF(C89="","",IF(C89>0,IF(S89<30,"Normal",IF(S89<60,"Especially Mentioned",IF(S89<90,"Substandard",IF(S89<=180,"Doubtful",IF(S89>180,"Loss","0"))))),"Not Applicable")) -> Substandard
A90: 2026/08/11 | B90: 2026/08/11 | C90: 500 | D90: 0 | E90: 101103g262230009 | H90: 11 AUG 26 05.59.43.640432 PM => 10109000006 BOT CLEARING USD via FLEXCUBE RTN 26086T000566388 625IBOT262120001 dd260731 Rsn Posted wrongly to us | S90: =IF(A90="","",A$5-A90) -> 76 | T90: =IF(S90="","",IF(S90<4,"0-3 Days",IF(S90<31,"4-30 Days",IF(S90<61,"31-60 Days",IF(S90<=90,"61-90 Days",IF(S90>90,"Above 90 Days","0")))))) -> 61-90 Days | U90: =IF(C90="","",IF(C90>0,IF(S90<30,"Normal",IF(S90<60,"Especially Mentioned",IF(S90<90,"Substandard",IF(S90<=180,"Doubtful",IF(S90>180,"Loss","0"))))),"Not Applicable")) -> Substandard
A91: 2026/08/11 | B91: 2026/08/11 | C91: 0 | D91: 5000 | E91: 408ZEXA26223007I | F91: 000008372241 | H91: Outgoing Funds Transfer 11 AUG 26 02.38.24.903856 PM OBDX from MAULY TOURS AND SAFARIS LTD to THE MANAGER IATA BSP HINGE ACCOUNT 8708020341500. Remark: IATA BILL NO 83201064 | S91: =IF(A91="","",A$5-A91) -> 76 | T91: =IF(S91="","",IF(S91<4,"0-3 Days",IF(S91<31,"4-30 Days",IF(S91<61,"31-60 Days",IF(S91<=90,"61-90 Days",IF(S91>90,"Above 90 Days","0")))))) -> 61-90 Days | U91: =IF(C91="","",IF(C91>0,IF(S91<30,"Normal",IF(S91<60,"Especially Mentioned",IF(S91<90,"Substandard",IF(S91<=180,"Doubtful",IF(S91>180,"Loss","0"))))),"Not Applicable")) -> Not Applicable
A92: 2026/08/13 | B92: 2026/08/13 | C92: 15000 | D92: 0 | E92: 219ZEXA262250007 | F92: 2608132608000054 | H92: Incoming Funds Transfer on 13 AUG 26 02.16.17.997907 PM from A CLASS MARBLE TANZANIA PRIVAT at . Remarks: SELF ACCOUNT TRANSFER | S92: =IF(A92="","",A$5-A92) -> 74 | T92: =IF(S92="","",IF(S92<4,"0-3 Days",IF(S92<31,"4-30 Days",IF(S92<61,"31-60 Days",IF(S92<=90,"61-90 Days",IF(S92>90,"Above 90 Days","0")))))) -> 61-90 Days | U92: =IF(C92="","",IF(C92>0,IF(S92<30,"Normal",IF(S92<60,"Especially Mentioned",IF(S92<90,"Substandard",IF(S92<=180,"Doubtful",IF(S92>180,"Loss","0"))))),"Not Applicable")) -> Substandard
A93: 2026/08/14 | B93: 2026/08/13 | C93: 0 | D93: 1920 | E93: 403ZEXA2622500UQ | F93: ACTZ9114620133 | H93: Outgoing Funds Transfer 14 AUG 26 05.07.28.638680 AM OBDX from MAKASA LIMITED to Zawadi Luxury Camps Limited 7036385522. Remark: | S93: =IF(A93="","",A$5-A93) -> 73 | T93: =IF(S93="","",IF(S93<4,"0-3 Days",IF(S93<31,"4-30 Days",IF(S93<61,"31-60 Days",IF(S93<=90,"61-90 Days",IF(S93>90,"Above 90 Days","0")))))) -> 61-90 Days | U93: =IF(C93="","",IF(C93>0,IF(S93<30,"Normal",IF(S93<60,"Especially Mentioned",IF(S93<90,"Substandard",IF(S93<=180,"Doubtful",IF(S93>180,"Loss","0"))))),"Not Applicable")) -> Not Applicable
A94: 2026/08/13 | B94: 2026/08/13 | C94: 0 | D94: 50 | E94: 225ZEXA262250025 | F94: CMC6038DC58D8B | H94: Outgoing Funds Transfer 13 AUG 26 01.52.55.929182 PM OBDX from JEREMIAH STANFORD LYIMO to Rhino Premium Auto parts 025959467200. Remark: | S94: =IF(A94="","",A$5-A94) -> 74 | T94: =IF(S94="","",IF(S94<4,"0-3 Days",IF(S94<31,"4-30 Days",IF(S94<61,"31-60 Days",IF(S94<=90,"61-90 Days",IF(S94>90,"Above 90 Days","0")))))) -> 61-90 Days | U94: =IF(C94="","",IF(C94>0,IF(S94<30,"Normal",IF(S94<60,"Especially Mentioned",IF(S94<90,"Substandard",IF(S94<=180,"Doubtful",IF(S94>180,"Loss","0"))))),"Not Applicable")) -> Not Applicable
A95: 2026/08/13 | B95: 2026/08/13 | C95: 600437.5 | D95: 0 | E95: 101o038262250001 | H95: 13 AUG 26 10.18.33.248401 PM => 10109000006 BOT CLEARING USD via OPICS 2011854 AZANIA | S95: =IF(A95="","",A$5-A95) -> 74 | T95: =IF(S95="","",IF(S95<4,"0-3 Days",IF(S95<31,"4-30 Days",IF(S95<61,"31-60 Days",IF(S95<=90,"61-90 Days",IF(S95>90,"Above 90 Days","0")))))) -> 61-90 Days | U95: =IF(C95="","",IF(C95>0,IF(S95<30,"Normal",IF(S95<60,"Especially Mentioned",IF(S95<90,"Substandard",IF(S95<=180,"Doubtful",IF(S95>180,"Loss","0"))))),"Not Applicable")) -> Substandard
A96: 2026/08/13 | B96: 2026/08/13 | C96: 0 | D96: 100000 | E96: 204ZEXA26225000O | F96: CM7F8ABE0287FE | H96: Outgoing Funds Transfer 13 AUG 26 12.03.09.653912 PM OBDX from ZANZIBAR MILLING CORPORATION to ZANZIBAR MILLING CORPORATION LIMITED 8704005472900. Remark: NMB TO SCB | S96: =IF(A96="","",A$5-A96) -> 74 | T96: =IF(S96="","",IF(S96<4,"0-3 Days",IF(S96<31,"4-30 Days",IF(S96<61,"31-60 Days",IF(S96<=90,"61-90 Days",IF(S96>90,"Above 90 Days","0")))))) -> 61-90 Days | U96: =IF(C96="","",IF(C96>0,IF(S96<30,"Normal",IF(S96<60,"Especially Mentioned",IF(S96<90,"Substandard",IF(S96<=180,"Doubtful",IF(S96>180,"Loss","0"))))),"Not Applicable")) -> Not Applicable
A97: 2026/08/15 | B97: 2026/08/14 | C97: 0 | D97: 4400 | E97: 408ZEXA262260151 | H97: Outgoing Funds Transfer FLEXCUBE from ELOTOTO TANZANIA LIMITED to VENTURE HARMONY SAFARIS LTD 022010001498. Remark: Long Lease car hire Q2 | S97: =IF(A97="","",A$5-A97) -> 72 | T97: =IF(S97="","",IF(S97<4,"0-3 Days",IF(S97<31,"4-30 Days",IF(S97<61,"31-60 Days",IF(S97<=90,"61-90 Days",IF(S97>90,"Above 90 Days","0")))))) -> 61-90 Days | U97: =IF(C97="","",IF(C97>0,IF(S97<30,"Normal",IF(S97<60,"Especially Mentioned",IF(S97<90,"Substandard",IF(S97<=180,"Doubtful",IF(S97>180,"Loss","0"))))),"Not Applicable")) -> Not Applicable
A98: 2026/08/15 | B98: 2026/08/14 | C98: 0 | D98: 3600 | E98: 408ZEXA26226006Z | H98: Outgoing Funds Transfer FLEXCUBE from ELOTOTO TANZANIA LIMITED to ETERNAL SERENGETI ADVENTURES LIMITED 10385085066. Remark: Long lease car hire T816 CET Q2 | S98: =IF(A98="","",A$5-A98) -> 72 | T98: =IF(S98="","",IF(S98<4,"0-3 Days",IF(S98<31,"4-30 Days",IF(S98<61,"31-60 Days",IF(S98<=90,"61-90 Days",IF(S98>90,"Above 90 Days","0")))))) -> 61-90 Days | U98: =IF(C98="","",IF(C98>0,IF(S98<30,"Normal",IF(S98<60,"Especially Mentioned",IF(S98<90,"Substandard",IF(S98<=180,"Doubtful",IF(S98>180,"Loss","0"))))),"Not Applicable")) -> Not Applicable
A99: 2026/08/15 | B99: 2026/08/14 | C99: 0 | D99: 353.2 | E99: 408ZEXA262260158 | H99: Outgoing Funds Transfer FLEXCUBE from SERENGETI CLARITY to MVULI HOTEL 3301316662. Remark: Vatslya x3 | S99: =IF(A99="","",A$5-A99) -> 72 | T99: =IF(S99="","",IF(S99<4,"0-3 Days",IF(S99<31,"4-30 Days",IF(S99<61,"31-60 Days",IF(S99<=90,"61-90 Days",IF(S99>90,"Above 90 Days","0")))))) -> 61-90 Days | U99: =IF(C99="","",IF(C99>0,IF(S99<30,"Normal",IF(S99<60,"Especially Mentioned",IF(S99<90,"Substandard",IF(S99<=180,"Doubtful",IF(S99>180,"Loss","0"))))),"Not Applicable")) -> Not Applicable
A100: 2026/08/14 | B100: 2026/08/14 | C100: 0 | D100: 600000 | E100: 101o038262260001 | H100: 14 AUG 26 08.34.07.694070 PM => 10109000006 BOT CLEARING USD via OPICS 2011898 AZANIA | S100: =IF(A100="","",A$5-A100) -> 73 | T100: =IF(S100="","",IF(S100<4,"0-3 Days",IF(S100<31,"4-30 Days",IF(S100<61,"31-60 Days",IF(S100<=90,"61-90 Days",IF(S100>90,"Above 90 Days","0")))))) -> 61-90 Days | U100: =IF(C100="","",IF(C100>0,IF(S100<30,"Normal",IF(S100<60,"Especially Mentioned",IF(S100<90,"Substandard",IF(S100<=180,"Doubtful",IF(S100>180,"Loss","0"))))),"Not Applicable")) -> Not Applicable
A101: 2026/08/15 | B101: 2026/08/14 | C101: 0 | D101: 1242.3 | E101: 408ZEXA262260157 | H101: Outgoing Funds Transfer FLEXCUBE from SERENGETI CLARITY to SERENGETI CLASSIC VIEW CA 0250000P94B00. Remark: Vatslya x3 | S101: =IF(A101="","",A$5-A101) -> 72 | T101: =IF(S101="","",IF(S101<4,"0-3 Days",IF(S101<31,"4-30 Days",IF(S101<61,"31-60 Days",IF(S101<=90,"61-90 Days",IF(S101>90,"Above 90 Days","0")))))) -> 61-90 Days | U101: =IF(C101="","",IF(C101>0,IF(S101<30,"Normal",IF(S101<60,"Especially Mentioned",IF(S101<90,"Substandard",IF(S101<=180,"Doubtful",IF(S101>180,"Loss","0"))))),"Not Applicable")) -> Not Applicable
A102: 2026/08/14 | B102: 2026/08/14 | C102: 14000 | D102: 0 | E102: 241ZEXA2622600U6 | F102: TAPBTZTZ20260814122151657 | H102: Incoming Funds Transfer on 14 AUG 26 01.29.39.068292 PM from Chen Jianshun Fujian at . Remarks: laan from shareholder | S102: =IF(A102="","",A$5-A102) -> 73 | T102: =IF(S102="","",IF(S102<4,"0-3 Days",IF(S102<31,"4-30 Days",IF(S102<61,"31-60 Days",IF(S102<=90,"61-90 Days",IF(S102>90,"Above 90 Days","0")))))) -> 61-90 Days | U102: =IF(C102="","",IF(C102>0,IF(S102<30,"Normal",IF(S102<60,"Especially Mentioned",IF(S102<90,"Substandard",IF(S102<=180,"Doubtful",IF(S102>180,"Loss","0"))))),"Not Applicable")) -> Substandard
A103: 2026/08/15 | B103: 2026/08/14 | C103: 0 | D103: 330 | E103: 428ZEXA2622600X6 | H103: Outgoing Funds Transfer FLEXCUBE from UTOPIA SAFARIS LIMITED to HERITAGE TENTED CAMPS 0250440170300. Remark: | S103: =IF(A103="","",A$5-A103) -> 72 | T103: =IF(S103="","",IF(S103<4,"0-3 Days",IF(S103<31,"4-30 Days",IF(S103<61,"31-60 Days",IF(S103<=90,"61-90 Days",IF(S103>90,"Above 90 Days","0")))))) -> 61-90 Days | U103: =IF(C103="","",IF(C103>0,IF(S103<30,"Normal",IF(S103<60,"Especially Mentioned",IF(S103<90,"Substandard",IF(S103<=180,"Doubtful",IF(S103>180,"Loss","0"))))),"Not Applicable")) -> Not Applicable
A104: 2026/08/14 | B104: 2026/08/14 | C104: 0 | D104: 1500000 | E104: 101o069262260001 | H104: 14 AUG 26 08.34.21.447978 PM => 10109000006 BOT CLEARING USD via OPICS 2011900 AZANIA | S104: =IF(A104="","",A$5-A104) -> 73 | T104: =IF(S104="","",IF(S104<4,"0-3 Days",IF(S104<31,"4-30 Days",IF(S104<61,"31-60 Days",IF(S104<=90,"61-90 Days",IF(S104>90,"Above 90 Days","0")))))) -> 61-90 Days | U104: =IF(C104="","",IF(C104>0,IF(S104<30,"Normal",IF(S104<60,"Especially Mentioned",IF(S104<90,"Substandard",IF(S104<=180,"Doubtful",IF(S104>180,"Loss","0"))))),"Not Applicable")) -> Not Applicable
A105: 2026/08/15 | B105: 2026/08/14 | C105: 0 | D105: 360 | E105: 408ZEXA262260071 | H105: Outgoing Funds Transfer FLEXCUBE from KILIMANJARO SKY LIMITED to KANKARI LODGE KARATU 045105001316. Remark: ELISABETTA 4 KILI SKY | S105: =IF(A105="","",A$5-A105) -> 72 | T105: =IF(S105="","",IF(S105<4,"0-3 Days",IF(S105<31,"4-30 Days",IF(S105<61,"31-60 Days",IF(S105<=90,"61-90 Days",IF(S105>90,"Above 90 Days","0")))))) -> 61-90 Days | U105: =IF(C105="","",IF(C105>0,IF(S105<30,"Normal",IF(S105<60,"Especially Mentioned",IF(S105<90,"Substandard",IF(S105<=180,"Doubtful",IF(S105>180,"Loss","0"))))),"Not Applicable")) -> Not Applicable
A106: 2026/08/15 | B106: 2026/08/14 | C106: 0 | D106: 4262.2 | E106: 408ZEXA262260156 | H106: Outgoing Funds Transfer FLEXCUBE from SERENGETI CLARITY to KON TIKI AFRICA COMPANY LIMITED 9120002501064. Remark: Michael x8 | S106: =IF(A106="","",A$5-A106) -> 72 | T106: =IF(S106="","",IF(S106<4,"0-3 Days",IF(S106<31,"4-30 Days",IF(S106<61,"31-60 Days",IF(S106<=90,"61-90 Days",IF(S106>90,"Above 90 Days","0")))))) -> 61-90 Days | U106: =IF(C106="","",IF(C106>0,IF(S106<30,"Normal",IF(S106<60,"Especially Mentioned",IF(S106<90,"Substandard",IF(S106<=180,"Doubtful",IF(S106>180,"Loss","0"))))),"Not Applicable")) -> Not Applicable
A107: 2026/08/14 | B107: 2026/08/14 | C107: 150000 | D107: 0 | E107: 101o068262260001 | H107: 14 AUG 26 08.34.20.912833 PM => 10109000006 BOT CLEARING USD via OPICS 1081347 DORMANTANZ USD TZS 2658.00000000 150000.0000 | S107: =IF(A107="","",A$5-A107) -> 73 | T107: =IF(S107="","",IF(S107<4,"0-3 Days",IF(S107<31,"4-30 Days",IF(S107<61,"31-60 Days",IF(S107<=90,"61-90 Days",IF(S107>90,"Above 90 Days","0")))))) -> 61-90 Days | U107: =IF(C107="","",IF(C107>0,IF(S107<30,"Normal",IF(S107<60,"Especially Mentioned",IF(S107<90,"Substandard",IF(S107<=180,"Doubtful",IF(S107>180,"Loss","0"))))),"Not Applicable")) -> Substandard
A108: 2026/08/14 | B108: 2026/08/14 | C108: 0 | D108: 560 | E108: 428ZEXA26226003S | F108: CTZ00026226QWFP | H108: Outgoing Funds Transfer 14 AUG 26 01.14.04.022113 PM OBDX from GATO NERO SAFARIS LIMITED to MOIVARO INVESTMENT AND TRADING LTD 9120003358680. Remark: ANTONINO | S108: =IF(A108="","",A$5-A108) -> 73 | T108: =IF(S108="","",IF(S108<4,"0-3 Days",IF(S108<31,"4-30 Days",IF(S108<61,"31-60 Days",IF(S108<=90,"61-90 Days",IF(S108>90,"Above 90 Days","0")))))) -> 61-90 Days | U108: =IF(C108="","",IF(C108>0,IF(S108<30,"Normal",IF(S108<60,"Especially Mentioned",IF(S108<90,"Substandard",IF(S108<=180,"Doubtful",IF(S108>180,"Loss","0"))))),"Not Applicable")) -> Not Applicable
...

Sheet External outstanding
A1: OUTSTANDING ITEMS IN THE STATEMENT
A5: ='Internal outstanding'!A5 -> 46321 | C5: =SUM(C8:C1048576) -> 2.6422489e+08 | D5: =SUM(D8:D1048576) -> 1.9248639e+08
A7: TRN Date | B7: Value Date | C7: DR | D7: CR | E7: TRN Reference | F7: Source Reference | G7: UETR No | H7: Narrative | I7: Transaction Type | J7: Aging | K7: AGING GROUP | L7: BOT Classification
A8: 2025/11/18 | B8: 2025/11/18 | C8: 1000 | D8: 0 | E8: 225IBOT253200007 | F8: 225IBOT253200007 | H8: NMIBTZTZ EQBLTZTZ | J8: =IF(A8="","",A$5-A8) -> 342 | K8: =IF(J8="","",IF(J8<4,"0-3 Days",IF(J8<31,"4-30 Days",IF(J8<61,"31-60 Days",IF(J8<=90,"61-90 Days",IF(J8>90,"Above 90 Days","0")))))) -> Above 90 Days | L8: =IF(C8="","",IF(C8>0,IF(J8<30,"Normal",IF(J8<60,"Especially Mentioned",IF(J8<90,"Substandard",IF(J8<=180,"Doubtful",IF(J8>180,"Loss","0"))))),"Not Applicable")) -> Loss
A9: 2026/01/18 | B9: 2026/01/18 | C9: 150 | D9: 0 | E9: E0PC7UK8 | F9: E0PC7UK8 | H9: NMIBTZTZ CORUTZTZXXX | J9: =IF(A9="","",A$5-A9) -> 281 | K9: =IF(J9="","",IF(J9<4,"0-3 Days",IF(J9<31,"4-30 Days",IF(J9<61,"31-60 Days",IF(J9<=90,"61-90 Days",IF(J9>90,"Above 90 Days","0")))))) -> Above 90 Days | L9: =IF(C9="","",IF(C9>0,IF(J9<30,"Normal",IF(J9<60,"Especially Mentioned",IF(J9<90,"Substandard",IF(J9<=180,"Doubtful",IF(J9>180,"Loss","0"))))),"Not Applicable")) -> Loss
A10: 2026/01/21 | B10: 2026/01/21 | C10: 210 | D10: 0 | E10: MNRPES5J | F10: MNRPES5J | H10: NMIBTZTZ SBICTZTXXXX | J10: =IF(A10="","",A$5-A10) -> 278 | K10: =IF(J10="","",IF(J10<4,"0-3 Days",IF(J10<31,"4-30 Days",IF(J10<61,"31-60 Days",IF(J10<=90,"61-90 Days",IF(J10>90,"Above 90 Days","0")))))) -> Above 90 Days | L10: =IF(C10="","",IF(C10>0,IF(J10<30,"Normal",IF(J10<60,"Especially Mentioned",IF(J10<90,"Substandard",IF(J10<=180,"Doubtful",IF(J10>180,"Loss","0"))))),"Not Applicable")) -> Loss
A11: 2026/02/04 | B11: 2026/02/04 | C11: 2860 | D11: 0 | E11: 505FTOC2534200A3 | F11: 505FTOC2534200A3 | H11: NMIBTZTZ CORUTZTZXXX | J11: =IF(A11="","",A$5-A11) -> 264 | K11: =IF(J11="","",IF(J11<4,"0-3 Days",IF(J11<31,"4-30 Days",IF(J11<61,"31-60 Days",IF(J11<=90,"61-90 Days",IF(J11>90,"Above 90 Days","0")))))) -> Above 90 Days | L11: =IF(C11="","",IF(C11>0,IF(J11<30,"Normal",IF(J11<60,"Especially Mentioned",IF(J11<90,"Substandard",IF(J11<=180,"Doubtful",IF(J11>180,"Loss","0"))))),"Not Applicable")) -> Loss
A12: 2026/04/13 | B12: 2026/04/13 | C12: 17369.6 | D12: 0 | E12: K66COFUV | F12: OT26099TZ0190617 | H12: NMIBTZTZ SBICTZTXXXX | J12: =IF(A12="","",A$5-A12) -> 196 | K12: =IF(J12="","",IF(J12<4,"0-3 Days",IF(J12<31,"4-30 Days",IF(J12<61,"31-60 Days",IF(J12<=90,"61-90 Days",IF(J12>90,"Above 90 Days","0")))))) -> Above 90 Days | L12: =IF(C12="","",IF(C12>0,IF(J12<30,"Normal",IF(J12<60,"Especially Mentioned",IF(J12<90,"Substandard",IF(J12<=180,"Doubtful",IF(J12>180,"Loss","0"))))),"Not Applicable")) -> Loss
A13: 2026/04/13 | B13: 2026/04/13 | C13: 250 | D13: 0 | E13: 8FGM3TM7 | F13: CMRTG26100000115 | H13: NMIBTZTZ DTKETZTZXXX | J13: =IF(A13="","",A$5-A13) -> 196 | K13: =IF(J13="","",IF(J13<4,"0-3 Days",IF(J13<31,"4-30 Days",IF(J13<61,"31-60 Days",IF(J13<=90,"61-90 Days",IF(J13>90,"Above 90 Days","0")))))) -> Above 90 Days | L13: =IF(C13="","",IF(C13>0,IF(J13<30,"Normal",IF(J13<60,"Especially Mentioned",IF(J13<90,"Substandard",IF(J13<=180,"Doubtful",IF(J13>180,"Loss","0"))))),"Not Applicable")) -> Loss
A14: 2026/04/13 | B14: 2026/04/13 | C14: 400 | D14: 0 | E14: IBJORDLF | F14: OT26103TZ0191198 | H14: NMIBTZTZ SBICTZTXXXX | J14: =IF(A14="","",A$5-A14) -> 196 | K14: =IF(J14="","",IF(J14<4,"0-3 Days",IF(J14<31,"4-30 Days",IF(J14<61,"31-60 Days",IF(J14<=90,"61-90 Days",IF(J14>90,"Above 90 Days","0")))))) -> Above 90 Days | L14: =IF(C14="","",IF(C14>0,IF(J14<30,"Normal",IF(J14<60,"Especially Mentioned",IF(J14<90,"Substandard",IF(J14<=180,"Doubtful",IF(J14>180,"Loss","0"))))),"Not Applicable")) -> Loss
A15: 2026/04/13 | B15: 2026/04/13 | C15: 9441.6 | D15: 0 | E15: H8LKA2IL | F15: R90RTGO260990211 | H15: NMIBTZTZ ECOCTZTZXXX | J15: =IF(A15="","",A$5-A15) -> 196 | K15: =IF(J15="","",IF(J15<4,"0-3 Days",IF(J15<31,"4-30 Days",IF(J15<61,"31-60 Days",IF(J15<=90,"61-90 Days",IF(J15>90,"Above 90 Days","0")))))) -> Above 90 Days | L15: =IF(C15="","",IF(C15>0,IF(J15<30,"Normal",IF(J15<60,"Especially Mentioned",IF(J15<90,"Substandard",IF(J15<=180,"Doubtful",IF(J15>180,"Loss","0"))))),"Not Applicable")) -> Loss
A16: 2026/04/13 | B16: 2026/04/13 | C16: 250 | D16: 0 | E16: DILD1VL4 | F16: CMRTG26100000116 | H16: NMIBTZTZ DTKETZTZXXX | J16: =IF(A16="","",A$5-A16) -> 196 | K16: =IF(J16="","",IF(J16<4,"0-3 Days",IF(J16<31,"4-30 Days",IF(J16<61,"31-60 Days",IF(J16<=90,"61-90 Days",IF(J16>90,"Above 90 Days","0")))))) -> Above 90 Days | L16: =IF(C16="","",IF(C16>0,IF(J16<30,"Normal",IF(J16<60,"Especially Mentioned",IF(J16<90,"Substandard",IF(J16<=180,"Doubtful",IF(J16>180,"Loss","0"))))),"Not Applicable")) -> Loss
A17: 2026/04/13 | B17: 2026/04/13 | C17: 50 | D17: 0 | E17: IAAIHCPK | F17: GEPGTR-7188187 | H17: NMIBTZTZ BARCTZTZXXX | J17: =IF(A17="","",A$5-A17) -> 196 | K17: =IF(J17="","",IF(J17<4,"0-3 Days",IF(J17<31,"4-30 Days",IF(J17<61,"31-60 Days",IF(J17<=90,"61-90 Days",IF(J17>90,"Above 90 Days","0")))))) -> Above 90 Days | L17: =IF(C17="","",IF(C17>0,IF(J17<30,"Normal",IF(J17<60,"Especially Mentioned",IF(J17<90,"Substandard",IF(J17<=180,"Doubtful",IF(J17>180,"Loss","0"))))),"Not Applicable")) -> Loss
A18: 2026/04/14 | B18: 2026/04/14 | C18: 1000 | D18: 0 | E18: FC340UK1 | F18: TZAAO09926HN1O4 | H18: NMIBTZTZ BARCTZTZXXX | J18: =IF(A18="","",A$5-A18) -> 195 | K18: =IF(J18="","",IF(J18<4,"0-3 Days",IF(J18<31,"4-30 Days",IF(J18<61,"31-60 Days",IF(J18<=90,"61-90 Days",IF(J18>90,"Above 90 Days","0")))))) -> Above 90 Days | L18: =IF(C18="","",IF(C18>0,IF(J18<30,"Normal",IF(J18<60,"Especially Mentioned",IF(J18<90,"Substandard",IF(J18<=180,"Doubtful",IF(J18>180,"Loss","0"))))),"Not Applicable")) -> Loss
A19: 2026/04/14 | B19: 2026/04/14 | C19: 890 | D19: 0 | E19: G9AAR3TQ | F19: GEPGTR-7188219 | H19: NMIBTZTZ BARCTZTZXXX | J19: =IF(A19="","",A$5-A19) -> 195 | K19: =IF(J19="","",IF(J19<4,"0-3 Days",IF(J19<31,"4-30 Days",IF(J19<61,"31-60 Days",IF(J19<=90,"61-90 Days",IF(J19>90,"Above 90 Days","0")))))) -> Above 90 Days | L19: =IF(C19="","",IF(C19>0,IF(J19<30,"Normal",IF(J19<60,"Especially Mentioned",IF(J19<90,"Substandard",IF(J19<=180,"Doubtful",IF(J19>180,"Loss","0"))))),"Not Applicable")) -> Loss
A20: 2026/06/17 | B20: 2026/06/17 | C20: 240 | D20: 0 | E20: USJD1CFK | F20: P260422C00000761 | H20: NMIBTZTZ EXTNTZTZXXX | I20: 202 FIT | J20: =IF(A20="","",A$5-A20) -> 131 | K20: =IF(J20="","",IF(J20<4,"0-3 Days",IF(J20<31,"4-30 Days",IF(J20<61,"31-60 Days",IF(J20<=90,"61-90 Days",IF(J20>90,"Above 90 Days","0")))))) -> Above 90 Days | L20: =IF(C20="","",IF(C20>0,IF(J20<30,"Normal",IF(J20<60,"Especially Mentioned",IF(J20<90,"Substandard",IF(J20<=180,"Doubtful",IF(J20>180,"Loss","0"))))),"Not Applicable")) -> Doubtful
A21: 2026/07/09 | B21: 2026/07/09 | C21: 0 | D21: 40 | E21: FT261916Q5GP | F21: FT261916Q5GP | H21: NMIBTZTZXXX NMIBTZTZ | I21: 103 SCCT | J21: =IF(A21="","",A$5-A21) -> 109 | K21: =IF(J21="","",IF(J21<4,"0-3 Days",IF(J21<31,"4-30 Days",IF(J21<61,"31-60 Days",IF(J21<=90,"61-90 Days",IF(J21>90,"Above 90 Days","0")))))) -> Above 90 Days | L21: =IF(C21="","",IF(C21>0,IF(J21<30,"Normal",IF(J21<60,"Especially Mentioned",IF(J21<90,"Substandard",IF(J21<=180,"Doubtful",IF(J21>180,"Loss","0"))))),"Not Applicable")) -> Not Applicable
A22: 2026/07/15 | B22: 2026/07/15 | C22: 0 | D22: 280 | E22: 000000569202 | F22: bf322df7-d45d-4fe7-8ca0-c5764d23895 | H22: IMBLTZTZ NMIBTZTZ | I22: 103 SCCT | J22: =IF(A22="","",A$5-A22) -> 103 | K22: =IF(J22="","",IF(J22<4,"0-3 Days",IF(J22<31,"4-30 Days",IF(J22<61,"31-60 Days",IF(J22<=90,"61-90 Days",IF(J22>90,"Above 90 Days","0")))))) -> Above 90 Days | L22: =IF(C22="","",IF(C22>0,IF(J22<30,"Normal",IF(J22<60,"Especially Mentioned",IF(J22<90,"Substandard",IF(J22<=180,"Doubtful",IF(J22>180,"Loss","0"))))),"Not Applicable")) -> Not Applicable
A23: 2026/07/16 | B23: 2026/07/16 | C23: 0 | D23: 1500 | E23: HZ1JTLLJKT7C7B27 | F23: HZ1JTLLJKT7C7B27 | H23: NMIBTZTZXXX NMIBTZTZ | I23: 103 SCCT | J23: =IF(A23="","",A$5-A23) -> 102 | K23: =IF(J23="","",IF(J23<4,"0-3 Days",IF(J23<31,"4-30 Days",IF(J23<61,"31-60 Days",IF(J23<=90,"61-90 Days",IF(J23>90,"Above 90 Days","0")))))) -> Above 90 Days | L23: =IF(C23="","",IF(C23>0,IF(J23<30,"Normal",IF(J23<60,"Especially Mentioned",IF(J23<90,"Substandard",IF(J23<=180,"Doubtful",IF(J23>180,"Loss","0"))))),"Not Applicable")) -> Not Applicable
A24: 2026/07/17 | B24: 2026/07/17 | C24: 0 | D24: 940 | E24: CMRTG26198000138 | F24: Notprovided | H24: NMIBTZTZXXX NMIBTZTZ | I24: 103 SCCT | J24: =IF(A24="","",A$5-A24) -> 101 | K24: =IF(J24="","",IF(J24<4,"0-3 Days",IF(J24<31,"4-30 Days",IF(J24<61,"31-60 Days",IF(J24<=90,"61-90 Days",IF(J24>90,"Above 90 Days","0")))))) -> Above 90 Days | L24: =IF(C24="","",IF(C24>0,IF(J24<30,"Normal",IF(J24<60,"Especially Mentioned",IF(J24<90,"Substandard",IF(J24<=180,"Doubtful",IF(J24>180,"Loss","0"))))),"Not Applicable")) -> Not Applicable
A25: 2026/07/23 | B25: 2026/07/23 | C25: 0 | D25: 637.2 | E25: CMRTG26203003580 | F25: Notprovided | H25: NMIBTZTZXXX NMIBTZTZ | I25: 103 SCCT | J25: =IF(A25="","",A$5-A25) -> 95 | K25: =IF(J25="","",IF(J25<4,"0-3 Days",IF(J25<31,"4-30 Days",IF(J25<61,"31-60 Days",IF(J25<=90,"61-90 Days",IF(J25>90,"Above 90 Days","0")))))) -> Above 90 Days | L25: =IF(C25="","",IF(C25>0,IF(J25<30,"Normal",IF(J25<60,"Especially Mentioned",IF(J25<90,"Substandard",IF(J25<=180,"Doubtful",IF(J25>180,"Loss","0"))))),"Not Applicable")) -> Not Applicable
A26: 2026/07/24 | B26: 2026/07/24 | C26: 0 | D26: 7882 | E26: R90RTGO262050285 | F26: R90RTGO262050285 | H26: NMIBTZTZXXX NMIBTZTZ | I26: 103 SCCT | J26: =IF(A26="","",A$5-A26) -> 94 | K26: =IF(J26="","",IF(J26<4,"0-3 Days",IF(J26<31,"4-30 Days",IF(J26<61,"31-60 Days",IF(J26<=90,"61-90 Days",IF(J26>90,"Above 90 Days","0")))))) -> Above 90 Days | L26: =IF(C26="","",IF(C26>0,IF(J26<30,"Normal",IF(J26<60,"Especially Mentioned",IF(J26<90,"Substandard",IF(J26<=180,"Doubtful",IF(J26>180,"Loss","0"))))),"Not Applicable")) -> Not Applicable
A27: 2026/07/27 | B27: 2026/07/27 | C27: 0 | D27: 70.6 | E27: P260727C00000503 | F27: 248IBOT262080518 | H27: NMIBTZTZXXX NMIBTZTZ | I27: 202 FIT | J27: =IF(A27="","",A$5-A27) -> 91 | K27: =IF(J27="","",IF(J27<4,"0-3 Days",IF(J27<31,"4-30 Days",IF(J27<61,"31-60 Days",IF(J27<=90,"61-90 Days",IF(J27>90,"Above 90 Days","0")))))) -> Above 90 Days | L27: =IF(C27="","",IF(C27>0,IF(J27<30,"Normal",IF(J27<60,"Especially Mentioned",IF(J27<90,"Substandard",IF(J27<=180,"Doubtful",IF(J27>180,"Loss","0"))))),"Not Applicable")) -> Not Applicable
A28: 2026/07/27 | B28: 2026/07/27 | C28: 0 | D28: 222 | E28: TISS/RTN/26/949 | F28: TISS/RTN/26/949 | H28: NMIBTZTZXXX NMIBTZTZ | I28: 506 RETURN | J28: =IF(A28="","",A$5-A28) -> 91 | K28: =IF(J28="","",IF(J28<4,"0-3 Days",IF(J28<31,"4-30 Days",IF(J28<61,"31-60 Days",IF(J28<=90,"61-90 Days",IF(J28>90,"Above 90 Days","0")))))) -> Above 90 Days | L28: =IF(C28="","",IF(C28>0,IF(J28<30,"Normal",IF(J28<60,"Especially Mentioned",IF(J28<90,"Substandard",IF(J28<=180,"Doubtful",IF(J28>180,"Loss","0"))))),"Not Applicable")) -> Not Applicable
A29: 2026/07/27 | B29: 2026/07/27 | C29: 0 | D29: 1110.86 | E29: TISS/RTN/26/953 | F29: TISS/RTN/26/953 | H29: NMIBTZTZXXX NMIBTZTZ | I29: 506 RETURN | J29: =IF(A29="","",A$5-A29) -> 91 | K29: =IF(J29="","",IF(J29<4,"0-3 Days",IF(J29<31,"4-30 Days",IF(J29<61,"31-60 Days",IF(J29<=90,"61-90 Days",IF(J29>90,"Above 90 Days","0")))))) -> Above 90 Days | L29: =IF(C29="","",IF(C29>0,IF(J29<30,"Normal",IF(J29<60,"Especially Mentioned",IF(J29<90,"Substandard",IF(J29<=180,"Doubtful",IF(J29>180,"Loss","0"))))),"Not Applicable")) -> Not Applicable
A30: 2026/07/28 | B30: 2026/07/28 | C30: 0 | D30: 80 | E30: CMBE07671F06A1 | F30: CMBE07671F06A1 | H30: NMIBTZTZXXX NMIBTZTZ | I30: 506 RETURN | J30: =IF(A30="","",A$5-A30) -> 90 | K30: =IF(J30="","",IF(J30<4,"0-3 Days",IF(J30<31,"4-30 Days",IF(J30<61,"31-60 Days",IF(J30<=90,"61-90 Days",IF(J30>90,"Above 90 Days","0")))))) -> 61-90 Days | L30: =IF(C30="","",IF(C30>0,IF(J30<30,"Normal",IF(J30<60,"Especially Mentioned",IF(J30<90,"Substandard",IF(J30<=180,"Doubtful",IF(J30>180,"Loss","0"))))),"Not Applicable")) -> Not Applicable
A31: 2026/07/28 | B31: 2026/07/28 | C31: 0 | D31: 280 | E31: P260728C00002987 | F31: 428IBOT262090588 | H31: NMIBTZTZXXX NMIBTZTZ | I31: 202 FIT | J31: =IF(A31="","",A$5-A31) -> 90 | K31: =IF(J31="","",IF(J31<4,"0-3 Days",IF(J31<31,"4-30 Days",IF(J31<61,"31-60 Days",IF(J31<=90,"61-90 Days",IF(J31>90,"Above 90 Days","0")))))) -> 61-90 Days | L31: =IF(C31="","",IF(C31>0,IF(J31<30,"Normal",IF(J31<60,"Especially Mentioned",IF(J31<90,"Substandard",IF(J31<=180,"Doubtful",IF(J31>180,"Loss","0"))))),"Not Applicable")) -> Not Applicable
... A810: 2026/08/18 | B810: 2026/08/18 | C810: 0 | D810: 400 | E810: 2622404771129000 | F810: TFRTN/0372/26 | H810: IMBLTZTZ NMIBTZTZ | I810: 506 RETURN | J810: =IF(A810="","",A$5-A810) -> 69 | K810: =IF(J810="","",IF(J810<4,"0-3 Days",IF(J810<31,"4-30 Days",IF(J810<61,"31-60 Days",IF(J810<=90,"61-90 Days",IF(J810>90,"Above 90 Days","0")))))) -> 61-90 Days | L810: =IF(C810="","",IF(C810>0,IF(J810<30,"Normal",IF(J810<60,"Especially Mentioned",IF(J810<90,"Substandard",IF(J810<=180,"Doubtful",IF(J810>180,"Loss","0"))))),"Not Applicable")) -> Not Applicable
A811: 2026/08/19 | B811: 2026/08/19 | C811: 0 | D811: 1000 | E811: GEPGTR-7190487 | F811: GEPGTR-7190487 | G811: ddfbc6d0-9115-4958-829e-3666c620b2d3 | H811: BARCTZTZXXX NMIBTZTZ | I811: 103 SCCT | J811: =IF(A811="","",A$5-A811) -> 68 | K811: =IF(J811="","",IF(J811<4,"0-3 Days",IF(J811<31,"4-30 Days",IF(J811<61,"31-60 Days",IF(J811<=90,"61-90 Days",IF(J811>90,"Above 90 Days","0")))))) -> 61-90 Days | L811: =IF(C811="","",IF(C811>0,IF(J811<30,"Normal",IF(J811<60,"Especially Mentioned",IF(J811<90,"Substandard",IF(J811<=180,"Doubtful",IF(J811>180,"Loss","0"))))),"Not Applicable")) -> Not Applicable
A812: 2026/08/19 | B812: 2026/08/19 | C812: 0 | D812: 1000 | E812: 000008383612 | F812: 000008383612 | G812: b24258b1-9f15-4e31-bb98-b430b364cbde | H812: NMIBTZTZXXX NMIBTZTZ | I812: 103 SCCT | J812: =IF(A812="","",A$5-A812) -> 68 | K812: =IF(J812="","",IF(J812<4,"0-3 Days",IF(J812<31,"4-30 Days",IF(J812<61,"31-60 Days",IF(J812<=90,"61-90 Days",IF(J812>90,"Above 90 Days","0")))))) -> 61-90 Days | L812: =IF(C812="","",IF(C812>0,IF(J812<30,"Normal",IF(J812<60,"Especially Mentioned",IF(J812<90,"Substandard",IF(J812<=180,"Doubtful",IF(J812>180,"Loss","0"))))),"Not Applicable")) -> Not Applicable
A813: 2026/08/19 | B813: 2026/08/19 | C813: 0 | D813: 1236 | E813: GEPGTR-7190498 | F813: GEPGTR-7190498 | G813: 77765b88-0325-47ff-93c8-2cc661147d06 | H813: BARCTZTZXXX NMIBTZTZ | I813: 103 SCCT | J813: =IF(A813="","",A$5-A813) -> 68 | K813: =IF(J813="","",IF(J813<4,"0-3 Days",IF(J813<31,"4-30 Days",IF(J813<61,"31-60 Days",IF(J813<=90,"61-90 Days",IF(J813>90,"Above 90 Days","0")))))) -> 61-90 Days | L813: =IF(C813="","",IF(C813>0,IF(J813<30,"Normal",IF(J813<60,"Especially Mentioned",IF(J813<90,"Substandard",IF(J813<=180,"Doubtful",IF(J813>180,"Loss","0"))))),"Not Applicable")) -> Not Applicable
A814: 2026/08/19 | B814: 2026/08/19 | C814: 0 | D814: 6725 | E814: TZ1OL260819025AZ | F814: PIKLMATZ01A01166 | G814: 2aa1ae46-834f-4df0-9038-9d001ee81940 | H814: NMIBTZTZXXX NMIBTZTZ | I814: 103 SCCT | J814: =IF(A814="","",A$5-A814) -> 68 | K814: =IF(J814="","",IF(J814<4,"0-3 Days",IF(J814<31,"4-30 Days",IF(J814<61,"31-60 Days",IF(J814<=90,"61-90 Days",IF(J814>90,"Above 90 Days","0")))))) -> 61-90 Days | L814: =IF(C814="","",IF(C814>0,IF(J814<30,"Normal",IF(J814<60,"Especially Mentioned",IF(J814<90,"Substandard",IF(J814<=180,"Doubtful",IF(J814>180,"Loss","0"))))),"Not Applicable")) -> Not Applicable
A815: 2026/08/19 | B815: 2026/08/19 | C815: 0 | D815: 26424 | E815: RTOMICC01084722 | F815: RTOMICC01084722 | G815: 33dce8a1-9f86-40c3-863a-803fef9bec55 | H815: NMIBTZTZXXX NMIBTZTZ | I815: 103 SCCT | J815: =IF(A815="","",A$5-A815) -> 68 | K815: =IF(J815="","",IF(J815<4,"0-3 Days",IF(J815<31,"4-30 Days",IF(J815<61,"31-60 Days",IF(J815<=90,"61-90 Days",IF(J815>90,"Above 90 Days","0")))))) -> 61-90 Days | L815: =IF(C815="","",IF(C815>0,IF(J815<30,"Normal",IF(J815<60,"Especially Mentioned",IF(J815<90,"Substandard",IF(J815<=180,"Doubtful",IF(J815>180,"Loss","0"))))),"Not Applicable")) -> Not Applicable
A816: 2026/08/19 | B816: 2026/08/19 | C816: 0 | D816: 1000 | E816: GEPGTR-7190486 | F816: GEPGTR-7190486 | G816: afda2e7f-907b-451b-b4a2-b47c8c913a88 | H816: BARCTZTZXXX NMIBTZTZ | I816: 103 SCCT | J816: =IF(A816="","",A$5-A816) -> 68 | K816: =IF(J816="","",IF(J816<4,"0-3 Days",IF(J816<31,"4-30 Days",IF(J816<61,"31-60 Days",IF(J816<=90,"61-90 Days",IF(J816>90,"Above 90 Days","0")))))) -> 61-90 Days | L816: =IF(C816="","",IF(C816>0,IF(J816<30,"Normal",IF(J816<60,"Especially Mentioned",IF(J816<90,"Substandard",IF(J816<=180,"Doubtful",IF(J816>180,"Loss","0"))))),"Not Applicable")) -> Not Applicable
A817: 2026/08/19 | B817: 2026/08/19 | C817: 0 | D817: 25024.5 | E817: OT26231TZ0124855 | F817: OT26231TZ0124855 | G817: 3e78d35a-8117-49e4-989f-7c5d01025267 | H817: NMIBTZTZXXX NMIBTZTZ | I817: 103 SCCT | J817: =IF(A817="","",A$5-A817) -> 68 | K817: =IF(J817="","",IF(J817<4,"0-3 Days",IF(J817<31,"4-30 Days",IF(J817<61,"31-60 Days",IF(J817<=90,"61-90 Days",IF(J817>90,"Above 90 Days","0")))))) -> 61-90 Days | L817: =IF(C817="","",IF(C817>0,IF(J817<30,"Normal",IF(J817<60,"Especially Mentioned",IF(J817<90,"Substandard",IF(J817<=180,"Doubtful",IF(J817>180,"Loss","0"))))),"Not Applicable")) -> Not Applicable
A818: 2026/08/19 | B818: 2026/08/19 | C818: 0 | D818: 1000 | E818: TZ1OL260819025AS | F818: PITBEATZ01A23538 | G818: 3e071772-ae6c-47b6-be50-560e1c12c4cd | H818: NMIBTZTZXXX NMIBTZTZ | I818: 103 SCCT | J818: =IF(A818="","",A$5-A818) -> 68 | K818: =IF(J818="","",IF(J818<4,"0-3 Days",IF(J818<31,"4-30 Days",IF(J818<61,"31-60 Days",IF(J818<=90,"61-90 Days",IF(J818>90,"Above 90 Days","0")))))) -> 61-90 Days | L818: =IF(C818="","",IF(C818>0,IF(J818<30,"Normal",IF(J818<60,"Especially Mentioned",IF(J818<90,"Substandard",IF(J818<=180,"Doubtful",IF(J818>180,"Loss","0"))))),"Not Applicable")) -> Not Applicable
A819: 2026/08/19 | B819: 2026/08/19 | C819: 0 | D819: 675 | E819: OT26231TZ0124838 | F819: OT26231TZ0124838 | G819: 53ad187a-17b8-4515-abeb-d47625d78749 | H819: NMIBTZTZXXX NMIBTZTZ | I819: 103 SCCT | J819: =IF(A819="","",A$5-A819) -> 68 | K819: =IF(J819="","",IF(J819<4,"0-3 Days",IF(J819<31,"4-30 Days",IF(J819<61,"31-60 Days",IF(J819<=90,"61-90 Days",IF(J819>90,"Above 90 Days","0")))))) -> 61-90 Days | L819: =IF(C819="","",IF(C819>0,IF(J819<30,"Normal",IF(J819<60,"Especially Mentioned",IF(J819<90,"Substandard",IF(J819<=180,"Doubtful",IF(J819>180,"Loss","0"))))),"Not Applicable")) -> Not Applicable
A820: 2026/08/19 | B820: 2026/08/19 | C820: 86 | D820: 0 | E820: C1GM09ET | F820: C1GM09ET | G820: 03fa66c4-a898-45cb-a855-01d5a97d054b | H820: NMIBTZTZ CORUTZTZXXX | I820: 506 RETURN | J820: =IF(A820="","",A$5-A820) -> 68 | K820: =IF(J820="","",IF(J820<4,"0-3 Days",IF(J820<31,"4-30 Days",IF(J820<61,"31-60 Days",IF(J820<=90,"61-90 Days",IF(J820>90,"Above 90 Days","0")))))) -> 61-90 Days | L820: =IF(C820="","",IF(C820>0,IF(J820<30,"Normal",IF(J820<60,"Especially Mentioned",IF(J820<90,"Substandard",IF(J820<=180,"Doubtful",IF(J820>180,"Loss","0"))))),"Not Applicable")) -> Substandard
A821: 2026/08/19 | B821: 2026/08/19 | C821: 4151 | D821: 0 | E821: GD7FU5HD | F821: GD7FU5HD | G821: 5190718d-ed8f-4d64-8c33-b979d7685251 | H821: NMIBTZTZ ECOCTZTZXXX | I821: 506 RETURN | J821: =IF(A821="","",A$5-A821) -> 68 | K821: =IF(J821="","",IF(J821<4,"0-3 Days",IF(J821<31,"4-30 Days",IF(J821<61,"31-60 Days",IF(J821<=90,"61-90 Days",IF(J821>90,"Above 90 Days","0")))))) -> 61-90 Days | L821: =IF(C821="","",IF(C821>0,IF(J821<30,"Normal",IF(J821<60,"Especially Mentioned",IF(J821<90,"Substandard",IF(J821<=180,"Doubtful",IF(J821>180,"Loss","0"))))),"Not Applicable")) -> Substandard
A822: 2026/08/19 | B822: 2026/08/19 | C822: 0 | D822: 1000 | E822: GEPGTR-7190512 | F822: GEPGTR-7190512 | G822: ea5071ce-cc14-4877-897f-04186780cb70 | H822: BARCTZTZXXX NMIBTZTZ | I822: 103 SCCT | J822: =IF(A822="","",A$5-A822) -> 68 | K822: =IF(J822="","",IF(J822<4,"0-3 Days",IF(J822<31,"4-30 Days",IF(J822<61,"31-60 Days",IF(J822<=90,"61-90 Days",IF(J822>90,"Above 90 Days","0")))))) -> 61-90 Days | L822: =IF(C822="","",IF(C822>0,IF(J822<30,"Normal",IF(J822<60,"Especially Mentioned",IF(J822<90,"Substandard",IF(J822<=180,"Doubtful",IF(J822>180,"Loss","0"))))),"Not Applicable")) -> Not Applicable
... A907: 2026/08/20 | B907: 2026/08/20 | C907: 1000 | D907: 0 | E907: K06SDQPB | F907: K06SDQPB | G907: b56d804b-8113-494b-93ed-f7a3079e6377 | H907: NMIBTZTZ SCBLTZTXXXX | I907: 506 RETURN | J907: =IF(A907="","",A$5-A907) -> 67 | K907: =IF(J907="","",IF(J907<4,"0-3 Days",IF(J907<31,"4-30 Days",IF(J907<61,"31-60 Days",IF(J907<=90,"61-90 Days",IF(J907>90,"Above 90 Days","0")))))) -> 61-90 Days | L907: =IF(C907="","",IF(C907>0,IF(J907<30,"Normal",IF(J907<60,"Especially Mentioned",IF(J907<90,"Substandard",IF(J907<=180,"Doubtful",IF(J907>180,"Loss","0"))))),"Not Applicable")) -> Substandard
A908: 2026/08/20 | B908: 2026/08/20 | C908: 14902.47 | D908: 0 | E908: 260820TA039720 | F908: 260820TA039720 | H908: NMIBTZTZ TACHTZTZ | I908: 701 NSI | J908: =IF(A908="","",A$5-A908) -> 67 | K908: =IF(J908="","",IF(J908<4,"0-3 Days",IF(J908<31,"4-30 Days",IF(J908<61,"31-60 Days",IF(J908<=90,"61-90 Days",IF(J908>90,"Above 90 Days","0")))))) -> 61-90 Days | L908: =IF(C908="","",IF(C908>0,IF(J908<30,"Normal",IF(J908<60,"Especially Mentioned",IF(J908<90,"Substandard",IF(J908<=180,"Doubtful",IF(J908>180,"Loss","0"))))),"Not Applicable")) -> Substandard
A909: 2026/08/20 | B909: 2026/08/20 | C909: 360 | D909: 0 | E909: 15083F9A092D | F909: 1508EA7EEF0C | G909: 4e7a5e53-4a78-42d0-862d-f138279a4dd4 | H909: NMIBTZTZ NLCBTZTXXXX | I909: 103 SCCT | J909: =IF(A909="","",A$5-A909) -> 67 | K909: =IF(J909="","",IF(J909<4,"0-3 Days",IF(J909<31,"4-30 Days",IF(J909<61,"31-60 Days",IF(J909<=90,"61-90 Days",IF(J909>90,"Above 90 Days","0")))))) -> 61-90 Days | L909: =IF(C909="","",IF(C909>0,IF(J909<30,"Normal",IF(J909<60,"Especially Mentioned",IF(J909<90,"Substandard",IF(J909<=180,"Doubtful",IF(J909>180,"Loss","0"))))),"Not Applicable")) -> Substandard
A910: 2026/08/20 | B910: 2026/08/20 | C910: 0 | D910: 2650 | E910: TZAAO23226HZG5G | F910: f3ff578d-20b8-44d3-80ea-24c4a0d7339 | G910: 350f3277-4e28-45a3-b328-0eb27107359b | H910: BARCTZTZXXX NMIBTZTZ | I910: 103 SCCT | J910: =IF(A910="","",A$5-A910) -> 67 | K910: =IF(J910="","",IF(J910<4,"0-3 Days",IF(J910<31,"4-30 Days",IF(J910<61,"31-60 Days",IF(J910<=90,"61-90 Days",IF(J910>90,"Above 90 Days","0")))))) -> 61-90 Days | L910: =IF(C910="","",IF(C910>0,IF(J910<30,"Normal",IF(J910<60,"Especially Mentioned",IF(J910<90,"Substandard",IF(J910<=180,"Doubtful",IF(J910>180,"Loss","0"))))),"Not Applicable")) -> Not Applicable
A911: 2026/08/20 | B911: 2026/08/20 | C911: 0 | D911: 2100 | E911: OT26232TZ0125188 | F911: OT26232TZ0125188 | G911: a85ef705-a723-4b59-87e5-302ae8cea7a2 | H911: NMIBTZTZXXX NMIBTZTZ | I911: 103 SCCT | J911: =IF(A911="","",A$5-A911) -> 67 | K911: =IF(J911="","",IF(J911<4,"0-3 Days",IF(J911<31,"4-30 Days",IF(J911<61,"31-60 Days",IF(J911<=90,"61-90 Days",IF(J911>90,"Above 90 Days","0")))))) -> 61-90 Days | L911: =IF(C911="","",IF(C911>0,IF(J911<30,"Normal",IF(J911<60,"Especially Mentioned",IF(J911<90,"Substandard",IF(J911<=180,"Doubtful",IF(J911>180,"Loss","0"))))),"Not Applicable")) -> Not Applicable
A912: 2026/08/21 | B912: 2026/08/21 | C912: 0 | D912: 1000 | E912: TZAAO23326H6SEM | F912: 1b74ba16-b9aa-4a26-8c66-9b5a6d5d9c1 | G912: 57e66c89-d229-4fc7-855f-bbab1a34d062 | H912: BARCTZTZXXX NMIBTZTZ | I912: 103 SCCT | J912: =IF(A912="","",A$5-A912) -> 66 | K912: =IF(J912="","",IF(J912<4,"0-3 Days",IF(J912<31,"4-30 Days",IF(J912<61,"31-60 Days",IF(J912<=90,"61-90 Days",IF(J912>90,"Above 90 Days","0")))))) -> 61-90 Days | L912: =IF(C912="","",IF(C912>0,IF(J912<30,"Normal",IF(J912<60,"Especially Mentioned",IF(J912<90,"Substandard",IF(J912<=180,"Doubtful",IF(J912>180,"Loss","0"))))),"Not Applicable")) -> Not Applicable
A913: 2026/08/21 | B913: 2026/08/21 | C913: 0 | D913: 1000 | E913: OT26233TZ0125505 | F913: OT26233TZ0125505 | G913: 30875f40-f94b-4186-a014-de42ab1efb5d | H913: NMIBTZTZXXX NMIBTZTZ | I913: 103 SCCT | J913: =IF(A913="","",A$5-A913) -> 66 | K913: =IF(J913="","",IF(J913<4,"0-3 Days",IF(J913<31,"4-30 Days",IF(J913<61,"31-60 Days",IF(J913<=90,"61-90 Days",IF(J913>90,"Above 90 Days","0")))))) -> 61-90 Days | L913: =IF(C913="","",IF(C913>0,IF(J913<30,"Normal",IF(J913<60,"Especially Mentioned",IF(J913<90,"Substandard",IF(J913<=180,"Doubtful",IF(J913>180,"Loss","0"))))),"Not Applicable")) -> Not Applicable
A914: 2026/08/21 | B914: 2026/08/21 | C914: 0 | D914: 2700 | E914: P260821C00001907 | F914: P260821C00001907 | G914: da49e230-9573-409a-991d-107f0f54f90b | H914: NMIBTZTZXXX NMIBTZTZ | I914: 103 SCCT | J914: =IF(A914="","",A$5-A914) -> 66 | K914: =IF(J914="","",IF(J914<4,"0-3 Days",IF(J914<31,"4-30 Days",IF(J914<61,"31-60 Days",IF(J914<=90,"61-90 Days",IF(J914>90,"Above 90 Days","0")))))) -> 61-90 Days | L914: =IF(C914="","",IF(C914>0,IF(J914<30,"Normal",IF(J914<60,"Especially Mentioned",IF(J914<90,"Substandard",IF(J914<=180,"Doubtful",IF(J914>180,"Loss","0"))))),"Not Applicable")) -> Not Applicable
A915: 2026/08/21 | B915: 2026/08/21 | C915: 0 | D915: 250 | E915: OT26233TZ0125554 | F915: OT26233TZ0125554 | G915: 4bdadcc1-31ea-413f-9105-1ea4739d28b1 | H915: NMIBTZTZXXX NMIBTZTZ | I915: 103 SCCT | J915: =IF(A915="","",A$5-A915) -> 66 | K915: =IF(J915="","",IF(J915<4,"0-3 Days",IF(J915<31,"4-30 Days",IF(J915<61,"31-60 Days",IF(J915<=90,"61-90 Days",IF(J915>90,"Above 90 Days","0")))))) -> 61-90 Days | L915: =IF(C915="","",IF(C915>0,IF(J915<30,"Normal",IF(J915<60,"Especially Mentioned",IF(J915<90,"Substandard",IF(J915<=180,"Doubtful",IF(J915>180,"Loss","0"))))),"Not Applicable")) -> Not Applicable
A916: 2026/08/21 | B916: 2026/08/21 | C916: 0 | D916: 62115.2 | E916: OT26233TZ0125515 | F916: OT26233TZ0125515 | G916: 19f1e029-f749-4d8d-bc4d-0b9358828ea2 | H916: NMIBTZTZXXX NMIBTZTZ | I916: 103 SCCT | J916: =IF(A916="","",A$5-A916) -> 66 | K916: =IF(J916="","",IF(J916<4,"0-3 Days",IF(J916<31,"4-30 Days",IF(J916<61,"31-60 Days",IF(J916<=90,"61-90 Days",IF(J916>90,"Above 90 Days","0")))))) -> 61-90 Days | L916: =IF(C916="","",IF(C916>0,IF(J916<30,"Normal",IF(J916<60,"Especially Mentioned",IF(J916<90,"Substandard",IF(J916<=180,"Doubtful",IF(J916>180,"Loss","0"))))),"Not Applicable")) -> Not Applicable
A917: 2026/08/21 | B917: 2026/08/21 | C917: 0 | D917: 150 | E917: TZAAO23326HXNVD | F917: F/TZA/DRT/AAO/20260821/00037249344 | G917: 21c9cb2d-b738-4a3a-8133-e6dee23f5c8c | H917: BARCTZTZXXX NMIBTZTZ | I917: 103 SCCT | J917: =IF(A917="","",A$5-A917) -> 66 | K917: =IF(J917="","",IF(J917<4,"0-3 Days",IF(J917<31,"4-30 Days",IF(J917<61,"31-60 Days",IF(J917<=90,"61-90 Days",IF(J917>90,"Above 90 Days","0")))))) -> 61-90 Days | L917: =IF(C917="","",IF(C917>0,IF(J917<30,"Normal",IF(J917<60,"Especially Mentioned",IF(J917<90,"Substandard",IF(J917<=180,"Doubtful",IF(J917>180,"Loss","0"))))),"Not Applicable")) -> Not Applicable
A918: 2026/08/21 | B918: 2026/08/21 | C918: 0 | D918: 212.4 | E918: TZAAO23326H2WBA | F918: 33b05b49-fc2b-4c0e-99c0-28ee48b1151 | G918: 5f869993-e636-47be-a169-e9ca1e5a8c93 | H918: BARCTZTZXXX NMIBTZTZ | I918: 103 SCCT | J918: =IF(A918="","",A$5-A918) -> 66 | K918: =IF(J918="","",IF(J918<4,"0-3 Days",IF(J918<31,"4-30 Days",IF(J918<61,"31-60 Days",IF(J918<=90,"61-90 Days",IF(J918>90,"Above 90 Days","0")))))) -> 61-90 Days | L918: =IF(C918="","",IF(C918>0,IF(J918<30,"Normal",IF(J918<60,"Especially Mentioned",IF(J918<90,"Substandard",IF(J918<=180,"Doubtful",IF(J918>180,"Loss","0"))))),"Not Applicable")) -> Not Applicable
A919: 2026/08/21 | B919: 2026/08/21 | C919: 0 | D919: 1150 | E919: FT26233B34ZK | F919: FT26233B34ZK | G919: 05a01ebf-dc75-4023-9148-dfd76d8e4c1e | H919: NMIBTZTZXXX NMIBTZTZ | I919: 103 SCCT | J919: =IF(A919="","",A$5-A919) -> 66 | K919: =IF(J919="","",IF(J919<4,"0-3 Days",IF(J919<31,"4-30 Days",IF(J919<61,"31-60 Days",IF(J919<=90,"61-90 Days",IF(J919>90,"Above 90 Days","0")))))) -> 61-90 Days | L919: =IF(C919="","",IF(C919>0,IF(J919<30,"Normal",IF(J919<60,"Especially Mentioned",IF(J919<90,"Substandard",IF(J919<=180,"Doubtful",IF(J919>180,"Loss","0"))))),"Not Applicable")) -> Not Applicable
A920: 2026/08/21 | B920: 2026/08/21 | C920: 0 | D920: 1000 | E920: OT26233TZ0125592 | F920: OT26233TZ0125592 | G920: fe283f58-7ebc-41c9-a6a7-b57de76ad519 | H920: NMIBTZTZXXX NMIBTZTZ | I920: 103 SCCT | J920: =IF(A920="","",A$5-A920) -> 66 | K920: =IF(J920="","",IF(J920<4,"0-3 Days",IF(J920<31,"4-30 Days",IF(J920<61,"31-60 Days",IF(J920<=90,"61-90 Days",IF(J920>90,"Above 90 Days","0")))))) -> 61-90 Days | L920: =IF(C920="","",IF(C920>0,IF(J920<30,"Normal",IF(J920<60,"Especially Mentioned",IF(J920<90,"Substandard",IF(J920<=180,"Doubtful",IF(J920>180,"Loss","0"))))),"Not Applicable")) -> Not Applicable
... A987: 2026/08/24 | B987: 2026/08/24 | C987: 0 | D987: 2050 | E987: TZAAO23626H3FIX | F987: f0ac95e1-514a-4a30-a5e8-91f165d4494 | G987: 9f2b1999-6ab5-44f0-9cd5-fe3682494006 | H987: BARCTZTZXXX NMIBTZTZ | I987: 103 SCCT | J987: =IF(A987="","",A$5-A987) -> 63 | K987: =IF(J987="","",IF(J987<4,"0-3 Days",IF(J987<31,"4-30 Days",IF(J987<61,"31-60 Days",IF(J987<=90,"61-90 Days",IF(J987>90,"Above 90 Days","0")))))) -> 61-90 Days | L987: =IF(C987="","",IF(C987>0,IF(J987<30,"Normal",IF(J987<60,"Especially Mentioned",IF(J987<90,"Substandard",IF(J987<=180,"Doubtful",IF(J987>180,"Loss","0"))))),"Not Applicable")) -> Not Applicable
A988: 2026/08/24 | B988: 2026/08/24 | C988: 0 | D988: 15099.1 | E988: 260824TA039764 | F988: 260824TA039764 | H988: TACHTZTZ NMIBTZTZ | I988: 701 NSI | J988: =IF(A988="","",A$5-A988) -> 63 | K988: =IF(J988="","",IF(J988<4,"0-3 Days",IF(J988<31,"4-30 Days",IF(J988<61,"31-60 Days",IF(J988<=90,"61-90 Days",IF(J988>90,"Above 90 Days","0")))))) -> 61-90 Days | L988: =IF(C988="","",IF(C988>0,IF(J988<30,"Normal",IF(J988<60,"Especially Mentioned",IF(J988<90,"Substandard",IF(J988<=180,"Doubtful",IF(J988>180,"Loss","0"))))),"Not Applicable")) -> Not Applicable
A989: 2026/08/24 | B989: 2026/08/24 | C989: 0 | D989: 648 | E989: TZAAO23626HMQD3 | F989: 3f23563d-53fb-4606-bdeb-68dba13c68c | G989: ae6d13b6-4c8f-4ff5-9d85-9a7b0a1ec9f4 | H989: BARCTZTZXXX NMIBTZTZ | I989: 103 SCCT | J989: =IF(A989="","",A$5-A989) -> 63 | K989: =IF(J989="","",IF(J989<4,"0-3 Days",IF(J989<31,"4-30 Days",IF(J989<61,"31-60 Days",IF(J989<=90,"61-90 Days",IF(J989>90,"Above 90 Days","0")))))) -> 61-90 Days | L989: =IF(C989="","",IF(C989>0,IF(J989<30,"Normal",IF(J989<60,"Especially Mentioned",IF(J989<90,"Substandard",IF(J989<=180,"Doubtful",IF(J989>180,"Loss","0"))))),"Not Applicable")) -> Not Applicable
A990: 2026/08/24 | B990: 2026/08/24 | C990: 0 | D990: 150 | E990: CMRTG26236000801 | F990: Notprovided | G990: dbc74902-7445-49d0-9a9b-044ad7d0a2c9 | H990: NMIBTZTZXXX NMIBTZTZ | I990: 103 SCCT | J990: =IF(A990="","",A$5-A990) -> 63 | K990: =IF(J990="","",IF(J990<4,"0-3 Days",IF(J990<31,"4-30 Days",IF(J990<61,"31-60 Days",IF(J990<=90,"61-90 Days",IF(J990>90,"Above 90 Days","0")))))) -> 61-90 Days | L990: =IF(C990="","",IF(C990>0,IF(J990<30,"Normal",IF(J990<60,"Especially Mentioned",IF(J990<90,"Substandard",IF(J990<=180,"Doubtful",IF(J990>180,"Loss","0"))))),"Not Applicable")) -> Not Applicable
A991: 2026/08/24 | B991: 2026/08/24 | C991: 0 | D991: 2832 | E991: TZ1RTGF262362643 | F991: NOTPROVIDED | G991: 052dc2c9-5980-4fb1-bb2c-55b33339316c | H991: NMIBTZTZXXX NMIBTZTZ | I991: 103 SCCT | J991: =IF(A991="","",A$5-A991) -> 63 | K991: =IF(J991="","",IF(J991<4,"0-3 Days",IF(J991<31,"4-30 Days",IF(J991<61,"31-60 Days",IF(J991<=90,"61-90 Days",IF(J991>90,"Above 90 Days","0")))))) -> 61-90 Days | L991: =IF(C991="","",IF(C991>0,IF(J991<30,"Normal",IF(J991<60,"Especially Mentioned",IF(J991<90,"Substandard",IF(J991<=180,"Doubtful",IF(J991>180,"Loss","0"))))),"Not Applicable")) -> Not Applicable
A992: 2026/08/24 | B992: 2026/08/24 | C992: 0 | D992: 1000 | E992: CME95BCE3F4691 | F992: CME95BCE3F4691 | G992: 0cfd3d25-291d-4510-bd07-a442f4b7d6ec | H992: NMIBTZTZXXX NMIBTZTZ | I992: 506 RETURN | J992: =IF(A992="","",A$5-A992) -> 63 | K992: =IF(J992="","",IF(J992<4,"0-3 Days",IF(J992<31,"4-30 Days",IF(J992<61,"31-60 Days",IF(J992<=90,"61-90 Days",IF(J992>90,"Above 90 Days","0")))))) -> 61-90 Days | L992: =IF(C992="","",IF(C992>0,IF(J992<30,"Normal",IF(J992<60,"Especially Mentioned",IF(J992<90,"Substandard",IF(J992<=180,"Doubtful",IF(J992>180,"Loss","0"))))),"Not Applicable")) -> Not Applicable
A993: 2026/08/24 | B993: 2026/08/24 | C993: 0 | D993: 1000 | E993: TZ1OL260824028M0 | F993: PISINOTZ01A28828 | G993: 98aba7b2-d508-4827-8b7e-2452b49e02e0 | H993: NMIBTZTZXXX NMIBTZTZ | I993: 103 SCCT | J993: =IF(A993="","",A$5-A993) -> 63 | K993: =IF(J993="","",IF(J993<4,"0-3 Days",IF(J993<31,"4-30 Days",IF(J993<61,"31-60 Days",IF(J993<=90,"61-90 Days",IF(J993>90,"Above 90 Days","0")))))) -> 61-90 Days | L993: =IF(C993="","",IF(C993>0,IF(J993<30,"Normal",IF(J993<60,"Especially Mentioned",IF(J993<90,"Substandard",IF(J993<=180,"Doubtful",IF(J993>180,"Loss","0"))))),"Not Applicable")) -> Not Applicable
A994: 2026/08/24 | B994: 2026/08/24 | C994: 0 | D994: 305 | E994: GEPGTR-7190580 | F994: GEPGTR-7190580 | G994: 574c98e5-55ff-4a6e-9980-1587f426350d | H994: BARCTZTZXXX NMIBTZTZ | I994: 103 SCCT | J994: =IF(A994="","",A$5-A994) -> 63 | K994: =IF(J994="","",IF(J994<4,"0-3 Days",IF(J994<31,"4-30 Days",IF(J994<61,"31-60 Days",IF(J994<=90,"61-90 Days",IF(J994>90,"Above 90 Days","0")))))) -> 61-90 Days | L994: =IF(C994="","",IF(C994>0,IF(J994<30,"Normal",IF(J994<60,"Especially Mentioned",IF(J994<90,"Substandard",IF(J994<=180,"Doubtful",IF(J994>180,"Loss","0"))))),"Not Applicable")) -> Not Applicable
A995: 2026/08/24 | B995: 2026/08/24 | C995: 0 | D995: 1000 | E995: TZ1OL260824028PY | F995: PISINOTZ01A28833 | G995: c0d71356-5950-4702-9137-896863602ac3 | H995: NMIBTZTZXXX NMIBTZTZ | I995: 103 SCCT | J995: =IF(A995="","",A$5-A995) -> 63 | K995: =IF(J995="","",IF(J995<4,"0-3 Days",IF(J995<31,"4-30 Days",IF(J995<61,"31-60 Days",IF(J995<=90,"61-90 Days",IF(J995>90,"Above 90 Days","0")))))) -> 61-90 Days | L995: =IF(C995="","",IF(C995>0,IF(J995<30,"Normal",IF(J995<60,"Especially Mentioned",IF(J995<90,"Substandard",IF(J995<=180,"Doubtful",IF(J995>180,"Loss","0"))))),"Not Applicable")) -> Not Applicable
A996: 2026/08/24 | B996: 2026/08/24 | C996: 0 | D996: 529 | E996: DTB/1525/2026 | F996: 2408D20C0252 | G996: d5accd43-407b-4daf-8344-1ccc3088f83c | H996: NMIBTZTZXXX NMIBTZTZ | I996: 202 FIT | J996: =IF(A996="","",A$5-A996) -> 63 | K996: =IF(J996="","",IF(J996<4,"0-3 Days",IF(J996<31,"4-30 Days",IF(J996<61,"31-60 Days",IF(J996<=90,"61-90 Days",IF(J996>90,"Above 90 Days","0")))))) -> 61-90 Days | L996: =IF(C996="","",IF(C996>0,IF(J996<30,"Normal",IF(J996<60,"Especially Mentioned",IF(J996<90,"Substandard",IF(J996<=180,"Doubtful",IF(J996>180,"Loss","0"))))),"Not Applicable")) -> Not Applicable
A997: 2026/08/24 | B997: 2026/08/24 | C997: 0 | D997: 2650 | E997: OT26236TZ0126338 | F997: OT26236TZ0126338 | G997: f23aa18b-6db0-4eb7-b36e-f96e312ff730 | H997: NMIBTZTZXXX NMIBTZTZ | I997: 103 SCCT | J997: =IF(A997="","",A$5-A997) -> 63 | K997: =IF(J997="","",IF(J997<4,"0-3 Days",IF(J997<31,"4-30 Days",IF(J997<61,"31-60 Days",IF(J997<=90,"61-90 Days",IF(J997>90,"Above 90 Days","0")))))) -> 61-90 Days | L997: =IF(C997="","",IF(C997>0,IF(J997<30,"Normal",IF(J997<60,"Especially Mentioned",IF(J997<90,"Substandard",IF(J997<=180,"Doubtful",IF(J997>180,"Loss","0"))))),"Not Applicable")) -> Not Applicable
A998: 2026/08/24 | B998: 2026/08/24 | C998: 0 | D998: 600 | E998: OT26236TZ0126229 | F998: OT26236TZ0126229 | G998: ef179e7b-7ae3-43a7-a0fe-6d14c4c84e8d | H998: NMIBTZTZXXX NMIBTZTZ | I998: 103 SCCT | J998: =IF(A998="","",A$5-A998) -> 63 | K998: =IF(J998="","",IF(J998<4,"0-3 Days",IF(J998<31,"4-30 Days",IF(J998<61,"31-60 Days",IF(J998<=90,"61-90 Days",IF(J998>90,"Above 90 Days","0")))))) -> 61-90 Days | L998: =IF(C998="","",IF(C998>0,IF(J998<30,"Normal",IF(J998<60,"Especially Mentioned",IF(J998<90,"Substandard",IF(J998<=180,"Doubtful",IF(J998>180,"Loss","0"))))),"Not Applicable")) -> Not Applicable
A999: 2026/08/24 | B999: 2026/08/24 | C999: 0 | D999: 80 | E999: DTB/1520/2026 | F999: 2208EB4F3A25 | G999: 54e13e8f-6db2-4029-82ca-b75a115846ec | H999: NMIBTZTZXXX NMIBTZTZ | I999: 202 FIT | J999: =IF(A999="","",A$5-A999) -> 63 | K999: =IF(J999="","",IF(J999<4,"0-3 Days",IF(J999<31,"4-30 Days",IF(J999<61,"31-60 Days",IF(J999<=90,"61-90 Days",IF(J999>90,"Above 90 Days","0")))))) -> 61-90 Days | L999: =IF(C999="","",IF(C999>0,IF(J999<30,"Normal",IF(J999<60,"Especially Mentioned",IF(J999<90,"Substandard",IF(J999<=180,"Doubtful",IF(J999>180,"Loss","0"))))),"Not Applicable")) -> Not Applicable
A1000: 2026/08/24 | B1000: 2026/08/24 | C1000: 0 | D1000: 1000 | E1000: TZ1OL260824028SB | F1000: 0813000100-2 | G1000: ea0109dd-af24-47d2-8a74-3b157a317929 | H1000: NMIBTZTZXXX NMIBTZTZ | I1000: 103 SCCT | J1000: =IF(A1000="","",A$5-A1000) -> 63 | K1000: =IF(J1000="","",IF(J1000<4,"0-3 Days",IF(J1000<31,"4-30 Days",IF(J1000<61,"31-60 Days",IF(J1000<=90,"61-90 Days",IF(J1000>90,"Above 90 Days","0")))))) -> 61-90 Days | L1000: =IF(C1000="","",IF(C1000>0,IF(J1000<30,"Normal",IF(J1000<60,"Especially Mentioned",IF(J1000<90,"Substandard",IF(J1000<=180,"Doubtful",IF(J1000>180,"Loss","0"))))),"Not Applicable")) -> Not Applicable
... A1022: 2026/08/26 | B1022: 2026/08/26 | C1022: 1000000 | D1022: 0 | E1022: 1081527 | F1022: 1081527 | G1022: c070671b-6bbd-4832-94f1-0e644491c9c3 | H1022: NMIBTZTZ BARCTZTZXXX | I1022: 103 SCCT | J1022: =IF(A1022="","",A$5-A1022) -> 61 | K1022: =IF(J1022="","",IF(J1022<4,"0-3 Days",IF(J1022<31,"4-30 Days",IF(J1022<61,"31-60 Days",IF(J1022<=90,"61-90 Days",IF(J1022>90,"Above 90 Days","0")))))) -> 61-90 Days | L1022: =IF(C1022="","",IF(C1022>0,IF(J1022<30,"Normal",IF(J1022<60,"Especially Mentioned",IF(J1022<90,"Substandard",IF(J1022<=180,"Doubtful",IF(J1022>180,"Loss","0"))))),"Not Applicable")) -> Substandard
A1023: 2026/08/26 | B1023: 2026/08/26 | C1023: 0 | D1023: 15150.46 | E1023: 260826TA039779 | F1023: 260826TA039779 | H1023: TACHTZTZ NMIBTZTZ | I1023: 701 NSI | J1023: =IF(A1023="","",A$5-A1023) -> 61 | K1023: =IF(J1023="","",IF(J1023<4,"0-3 Days",IF(J1023<31,"4-30 Days",IF(J1023<61,"31-60 Days",IF(J1023<=90,"61-90 Days",IF(J1023>90,"Above 90 Days","0")))))) -> 61-90 Days | L1023: =IF(C1023="","",IF(C1023>0,IF(J1023<30,"Normal",IF(J1023<60,"Especially Mentioned",IF(J1023<90,"Substandard",IF(J1023<=180,"Doubtful",IF(J1023>180,"Loss","0"))))),"Not Applicable")) -> Not Applicable
A1024: 2026/08/26 | B1024: 2026/08/26 | C1024: 0 | D1024: 1000 | E1024: OT26238TZ0126498 | F1024: OT26238TZ0126498 | G1024: 372ee8e0-ae2c-42b3-a826-96e50c468fbe | H1024: NMIBTZTZXXX NMIBTZTZ | I1024: 103 SCCT | J1024: =IF(A1024="","",A$5-A1024) -> 61 | K1024: =IF(J1024="","",IF(J1024<4,"0-3 Days",IF(J1024<31,"4-30 Days",IF(J1024<61,"31-60 Days",IF(J1024<=90,"61-90 Days",IF(J1024>90,"Above 90 Days","0")))))) -> 61-90 Days | L1024: =IF(C1024="","",IF(C1024>0,IF(J1024<30,"Normal",IF(J1024<60,"Especially Mentioned",IF(J1024<90,"Substandard",IF(J1024<=180,"Doubtful",IF(J1024>180,"Loss","0"))))),"Not Applicable")) -> Not Applicable
A1025: 2026/08/26 | B1025: 2026/08/26 | C1025: 0 | D1025: 1000 | E1025: CMRTG26238002141 | F1025: Notprovided | G1025: c1333e6a-cf92-481c-9510-fcf85501ec52 | H1025: NMIBTZTZXXX NMIBTZTZ | I1025: 103 SCCT | J1025: =IF(A1025="","",A$5-A1025) -> 61 | K1025: =IF(J1025="","",IF(J1025<4,"0-3 Days",IF(J1025<31,"4-30 Days",IF(J1025<61,"31-60 Days",IF(J1025<=90,"61-90 Days",IF(J1025>90,"Above 90 Days","0")))))) -> 61-90 Days | L1025: =IF(C1025="","",IF(C1025>0,IF(J1025<30,"Normal",IF(J1025<60,"Especially Mentioned",IF(J1025<90,"Substandard",IF(J1025<=180,"Doubtful",IF(J1025>180,"Loss","0"))))),"Not Applicable")) -> Not Applicable
A1026: 2026/08/26 | B1026: 2026/08/26 | C1026: 0 | D1026: 347 | E1026: TZ5IL2608260005O | F1026: 2608FC287AC1 | G1026: 6765a1c5-3307-41b8-bb37-4407634f64d7 | H1026: NMIBTZTZXXX NMIBTZTZ | I1026: 202 FIT | J1026: =IF(A1026="","",A$5-A1026) -> 61 | K1026: =IF(J1026="","",IF(J1026<4,"0-3 Days",IF(J1026<31,"4-30 Days",IF(J1026<61,"31-60 Days",IF(J1026<=90,"61-90 Days",IF(J1026>90,"Above 90 Days","0")))))) -> 61-90 Days | L1026: =IF(C1026="","",IF(C1026>0,IF(J1026<30,"Normal",IF(J1026<60,"Especially Mentioned",IF(J1026<90,"Substandard",IF(J1026<=180,"Doubtful",IF(J1026>180,"Loss","0"))))),"Not Applicable")) -> Not Applicable
A1027: 2026/08/26 | B1027: 2026/08/26 | C1027: 0 | D1027: 33 | E1027: FT262383GLKS | F1027: FT262383GLKS | G1027: 879d3253-4eb1-49bf-90e3-90234abff625 | H1027: NMIBTZTZXXX NMIBTZTZ | I1027: 103 SCCT | J1027: =IF(A1027="","",A$5-A1027) -> 61 | K1027: =IF(J1027="","",IF(J1027<4,"0-3 Days",IF(J1027<31,"4-30 Days",IF(J1027<61,"31-60 Days",IF(J1027<=90,"61-90 Days",IF(J1027>90,"Above 90 Days","0")))))) -> 61-90 Days | L1027: =IF(C1027="","",IF(C1027>0,IF(J1027<30,"Normal",IF(J1027<60,"Especially Mentioned",IF(J1027<90,"Substandard",IF(J1027<=180,"Doubtful",IF(J1027>180,"Loss","0"))))),"Not Applicable")) -> Not Applicable
A1028: 2026/08/26 | B1028: 2026/08/26 | C1028: 0 | D1028: 969 | E1028: HZ1K0UCL9AH75A92 | F1028: HZ1K0UCL9AH75A92 | G1028: 0874a9b8-1efc-4a37-bd5e-c102ddc02b87 | H1028: NMIBTZTZXXX NMIBTZTZ | I1028: 103 SCCT | J1028: =IF(A1028="","",A$5-A1028) -> 61 | K1028: =IF(J1028="","",IF(J1028<4,"0-3 Days",IF(J1028<31,"4-30 Days",IF(J1028<61,"31-60 Days",IF(J1028<=90,"61-90 Days",IF(J1028>90,"Above 90 Days","0")))))) -> 61-90 Days | L1028: =IF(C1028="","",IF(C1028>0,IF(J1028<30,"Normal",IF(J1028<60,"Especially Mentioned",IF(J1028<90,"Substandard",IF(J1028<=180,"Doubtful",IF(J1028>180,"Loss","0"))))),"Not Applicable")) -> Not Applicable
A1029: 2026/08/26 | B1029: 2026/08/26 | C1029: 0 | D1029: 1000 | E1029: TZ1OL260826025R1 | F1029: PIGCN01979A10871 | G1029: 8ac61ab9-edee-4edb-ab94-06a66756d68f | H1029: NMIBTZTZXXX NMIBTZTZ | I1029: 103 SCCT | J1029: =IF(A1029="","",A$5-A1029) -> 61 | K1029: =IF(J1029="","",IF(J1029<4,"0-3 Days",IF(J1029<31,"4-30 Days",IF(J1029<61,"31-60 Days",IF(J1029<=90,"61-90 Days",IF(J1029>90,"Above 90 Days","0")))))) -> 61-90 Days | L1029: =IF(C1029="","",IF(C1029>0,IF(J1029<30,"Normal",IF(J1029<60,"Especially Mentioned",IF(J1029<90,"Substandard",IF(J1029<=180,"Doubtful",IF(J1029>180,"Loss","0"))))),"Not Applicable")) -> Not Applicable
A1030: 2026/08/26 | B1030: 2026/08/26 | C1030: 0 | D1030: 601.8 | E1030: OT26238TZ0126513 | F1030: OT26238TZ0126513 | G1030: 42ba93be-2300-465e-87ec-7b3c37ac28ea | H1030: NMIBTZTZXXX NMIBTZTZ | I1030: 103 SCCT | J1030: =IF(A1030="","",A$5-A1030) -> 61 | K1030: =IF(J1030="","",IF(J1030<4,"0-3 Days",IF(J1030<31,"4-30 Days",IF(J1030<61,"31-60 Days",IF(J1030<=90,"61-90 Days",IF(J1030>90,"Above 90 Days","0")))))) -> 61-90 Days | L1030: =IF(C1030="","",IF(C1030>0,IF(J1030<30,"Normal",IF(J1030<60,"Especially Mentioned",IF(J1030<90,"Substandard",IF(J1030<=180,"Doubtful",IF(J1030>180,"Loss","0"))))),"Not Applicable")) -> Not Applicable
A1031: 2026/08/26 | B1031: 2026/08/26 | C1031: 0 | D1031: 1000 | E1031: TZ1OL260824028U9 | F1031: PIDHTLTZ01A09021 | G1031: 4a8ac4ec-0140-44ba-a858-dcbd115cb1b5 | H1031: NMIBTZTZXXX NMIBTZTZ | I1031: 103 SCCT | J1031: =IF(A1031="","",A$5-A1031) -> 61 | K1031: =IF(J1031="","",IF(J1031<4,"0-3 Days",IF(J1031<31,"4-30 Days",IF(J1031<61,"31-60 Days",IF(J1031<=90,"61-90 Days",IF(J1031>90,"Above 90 Days","0")))))) -> 61-90 Days | L1031: =IF(C1031="","",IF(C1031>0,IF(J1031<30,"Normal",IF(J1031<60,"Especially Mentioned",IF(J1031<90,"Substandard",IF(J1031<=180,"Doubtful",IF(J1031>180,"Loss","0"))))),"Not Applicable")) -> Not Applicable
A1032: 2026/08/26 | B1032: 2026/08/26 | C1032: 0 | D1032: 1000 | E1032: OT26238TZ0126501 | F1032: OT26238TZ0126501 | G1032: 4a5dd2c9-e30c-47e9-b2a2-3c7804e632a2 | H1032: NMIBTZTZXXX NMIBTZTZ | I1032: 103 SCCT | J1032: =IF(A1032="","",A$5-A1032) -> 61 | K1032: =IF(J1032="","",IF(J1032<4,"0-3 Days",IF(J1032<31,"4-30 Days",IF(J1032<61,"31-60 Days",IF(J1032<=90,"61-90 Days",IF(J1032>90,"Above 90 Days","0")))))) -> 61-90 Days | L1032: =IF(C1032="","",IF(C1032>0,IF(J1032<30,"Normal",IF(J1032<60,"Especially Mentioned",IF(J1032<90,"Substandard",IF(J1032<=180,"Doubtful",IF(J1032>180,"Loss","0"))))),"Not Applicable")) -> Not Applicable
A1033: 2026/08/26 | B1033: 2026/08/26 | C1033: 0 | D1033: 14653.5 | E1033: R90RTGO262380403 | F1033: R90RTGO262380403 | G1033: 59be6ae8-5273-4c71-9c89-9cb22d4aa1b5 | H1033: NMIBTZTZXXX NMIBTZTZ | I1033: 103 SCCT | J1033: =IF(A1033="","",A$5-A1033) -> 61 | K1033: =IF(J1033="","",IF(J1033<4,"0-3 Days",IF(J1033<31,"4-30 Days",IF(J1033<61,"31-60 Days",IF(J1033<=90,"61-90 Days",IF(J1033>90,"Above 90 Days","0")))))) -> 61-90 Days | L1033: =IF(C1033="","",IF(C1033>0,IF(J1033<30,"Normal",IF(J1033<60,"Especially Mentioned",IF(J1033<90,"Substandard",IF(J1033<=180,"Doubtful",IF(J1033>180,"Loss","0"))))),"Not Applicable")) -> Not Applicable
A1034: 2026/08/26 | B1034: 2026/08/26 | C1034: 300000 | D1034: 0 | E1034: 1081514 | F1034: 1081514 | G1034: 8242eb52-767c-449a-b5e5-b6e5fe65227a | H1034: NMIBTZTZ CORUTZTZXXX | I1034: 103 SCCT | J1034: =IF(A1034="","",A$5-A1034) -> 61 | K1034: =IF(J1034="","",IF(J1034<4,"0-3 Days",IF(J1034<31,"4-30 Days",IF(J1034<61,"31-60 Days",IF(J1034<=90,"61-90 Days",IF(J1034>90,"Above 90 Days","0")))))) -> 61-90 Days | L1034: =IF(C1034="","",IF(C1034>0,IF(J1034<30,"Normal",IF(J1034<60,"Especially Mentioned",IF(J1034<90,"Substandard",IF(J1034<=180,"Doubtful",IF(J1034>180,"Loss","0"))))),"Not Applicable")) -> Substandard
A1035: 2026/08/26 | B1035: 2026/08/26 | C1035: 0 | D1035: 304 | E1035: OT26238TZ0126415 | F1035: OT26238TZ0126415 | G1035: 2819388a-bdbc-47aa-ad92-c7207f9246f6 | H1035: NMIBTZTZXXX NMIBTZTZ | I1035: 103 SCCT | J1035: =IF(A1035="","",A$5-A1035) -> 61 | K1035: =IF(J1035="","",IF(J1035<4,"0-3 Days",IF(J1035<31,"4-30 Days",IF(J1035<61,"31-60 Days",IF(J1035<=90,"61-90 Days",IF(J1035>90,"Above 90 Days","0")))))) -> 61-90 Days | L1035: =IF(C1035="","",IF(C1035>0,IF(J1035<30,"Normal",IF(J1035<60,"Especially Mentioned",IF(J1035<90,"Substandard",IF(J1035<=180,"Doubtful",IF(J1035>180,"Loss","0"))))),"Not Applicable")) -> Not Applicable
... A1126: 2026/08/27 | B1126: 2026/08/27 | C1126: 0 | D1126: 95 | E1126: TZAAO23926HH8UE | F1126: f623665a-6103-48c8-b5cc-fd1f1348fd9 | G1126: 266ab2f9-7a7e-4305-99d6-d4f092671221 | H1126: BARCTZTZXXX NMIBTZTZ | I1126: 103 SCCT | J1126: =IF(A1126="","",A$5-A1126) -> 60 | K1126: =IF(J1126="","",IF(J1126<4,"0-3 Days",IF(J1126<31,"4-30 Days",IF(J1126<61,"31-60 Days",IF(J1126<=90,"61-90 Days",IF(J1126>90,"Above 90 Days","0")))))) -> 31-60 Days | L1126: =IF(C1126="","",IF(C1126>0,IF(J1126<30,"Normal",IF(J1126<60,"Especially Mentioned",IF(J1126<90,"Substandard",IF(J1126<=180,"Doubtful",IF(J1126>180,"Loss","0"))))),"Not Applicable")) -> Not Applicable
A1127: 2026/08/27 | B1127: 2026/08/27 | C1127: 0 | D1127: 29899.09 | E1127: 260827TA039793 | F1127: 260827TA039793 | H1127: TACHTZTZ NMIBTZTZ | I1127: 701 NSI | J1127: =IF(A1127="","",A$5-A1127) -> 60 | K1127: =IF(J1127="","",IF(J1127<4,"0-3 Days",IF(J1127<31,"4-30 Days",IF(J1127<61,"31-60 Days",IF(J1127<=90,"61-90 Days",IF(J1127>90,"Above 90 Days","0")))))) -> 31-60 Days | L1127: =IF(C1127="","",IF(C1127>0,IF(J1127<30,"Normal",IF(J1127<60,"Especially Mentioned",IF(J1127<90,"Substandard",IF(J1127<=180,"Doubtful",IF(J1127>180,"Loss","0"))))),"Not Applicable")) -> Not Applicable
A1128: 2026/08/27 | B1128: 2026/08/27 | C1128: 0 | D1128: 2150 | E1128: TZAAO23926HYWGR | F1128: c55d5a56-c583-490d-96ed-4723bf80219 | G1128: 00414adf-7b28-4603-a13f-270b2173fbc7 | H1128: BARCTZTZXXX NMIBTZTZ | I1128: 103 SCCT | J1128: =IF(A1128="","",A$5-A1128) -> 60 | K1128: =IF(J1128="","",IF(J1128<4,"0-3 Days",IF(J1128<31,"4-30 Days",IF(J1128<61,"31-60 Days",IF(J1128<=90,"61-90 Days",IF(J1128>90,"Above 90 Days","0")))))) -> 31-60 Days | L1128: =IF(C1128="","",IF(C1128>0,IF(J1128<30,"Normal",IF(J1128<60,"Especially Mentioned",IF(J1128<90,"Substandard",IF(J1128<=180,"Doubtful",IF(J1128>180,"Loss","0"))))),"Not Applicable")) -> Not Applicable
A1129: 2026/08/27 | B1129: 2026/08/27 | C1129: 110000 | D1129: 0 | E1129: 1081533 | F1129: 1081533 | G1129: caaf8d9d-7ee6-43f5-ac6b-bdbeb7a398a8 | H1129: NMIBTZTZ CORUTZTZXXX | I1129: 103 SCCT | J1129: =IF(A1129="","",A$5-A1129) -> 60 | K1129: =IF(J1129="","",IF(J1129<4,"0-3 Days",IF(J1129<31,"4-30 Days",IF(J1129<61,"31-60 Days",IF(J1129<=90,"61-90 Days",IF(J1129>90,"Above 90 Days","0")))))) -> 31-60 Days | L1129: =IF(C1129="","",IF(C1129>0,IF(J1129<30,"Normal",IF(J1129<60,"Especially Mentioned",IF(J1129<90,"Substandard",IF(J1129<=180,"Doubtful",IF(J1129>180,"Loss","0"))))),"Not Applicable")) -> Substandard
A1130: 2026/08/27 | B1130: 2026/08/27 | C1130: 840975.54 | D1130: 0 | E1130: 311LC02261770002 | F1130: 311LC02261770002 | G1130: 25b04e26-cc60-4866-bc2f-05286e8f73ba | H1130: NMIBTZTZ CORUTZTZXXX | I1130: 202 FIT | J1130: =IF(A1130="","",A$5-A1130) -> 60 | K1130: =IF(J1130="","",IF(J1130<4,"0-3 Days",IF(J1130<31,"4-30 Days",IF(J1130<61,"31-60 Days",IF(J1130<=90,"61-90 Days",IF(J1130>90,"Above 90 Days","0")))))) -> 31-60 Days | L1130: =IF(C1130="","",IF(C1130>0,IF(J1130<30,"Normal",IF(J1130<60,"Especially Mentioned",IF(J1130<90,"Substandard",IF(J1130<=180,"Doubtful",IF(J1130>180,"Loss","0"))))),"Not Applicable")) -> Substandard
A1131: 2026/08/28 | B1131: 2026/08/28 | C1131: 0 | D1131: 250 | E1131: S486014 | F1131: S486014 | G1131: dfc343e7-8cc3-4c5a-96d6-3668a45f7cea | H1131: NMIBTZTZXXX NMIBTZTZ | I1131: 103 SCCT | J1131: =IF(A1131="","",A$5-A1131) -> 59 | K1131: =IF(J1131="","",IF(J1131<4,"0-3 Days",IF(J1131<31,"4-30 Days",IF(J1131<61,"31-60 Days",IF(J1131<=90,"61-90 Days",IF(J1131>90,"Above 90 Days","0")))))) -> 31-60 Days | L1131: =IF(C1131="","",IF(C1131>0,IF(J1131<30,"Normal",IF(J1131<60,"Especially Mentioned",IF(J1131<90,"Substandard",IF(J1131<=180,"Doubtful",IF(J1131>180,"Loss","0"))))),"Not Applicable")) -> Not Applicable
A1132: 2026/08/28 | B1132: 2026/08/28 | C1132: 0 | D1132: 4125 | E1132: TZ1RTGF262400933 | F1132: NOTPROVIDED | G1132: 0c5ffc40-e8a7-40ac-b3dd-fac21ad7960e | H1132: NMIBTZTZXXX NMIBTZTZ | I1132: 103 SCCT | J1132: =IF(A1132="","",A$5-A1132) -> 59 | K1132: =IF(J1132="","",IF(J1132<4,"0-3 Days",IF(J1132<31,"4-30 Days",IF(J1132<61,"31-60 Days",IF(J1132<=90,"61-90 Days",IF(J1132>90,"Above 90 Days","0")))))) -> 31-60 Days | L1132: =IF(C1132="","",IF(C1132>0,IF(J1132<30,"Normal",IF(J1132<60,"Especially Mentioned",IF(J1132<90,"Substandard",IF(J1132<=180,"Doubtful",IF(J1132>180,"Loss","0"))))),"Not Applicable")) -> Not Applicable
A1133: 2026/08/28 | B1133: 2026/08/28 | C1133: 0 | D1133: 1000 | E1133: TZ1RTGF262400666 | F1133: NOTPROVIDED | G1133: 63855d29-ea20-4d1f-86fd-1ac934ab467a | H1133: NMIBTZTZXXX NMIBTZTZ | I1133: 103 SCCT | J1133: =IF(A1133="","",A$5-A1133) -> 59 | K1133: =IF(J1133="","",IF(J1133<4,"0-3 Days",IF(J1133<31,"4-30 Days",IF(J1133<61,"31-60 Days",IF(J1133<=90,"61-90 Days",IF(J1133>90,"Above 90 Days","0")))))) -> 31-60 Days | L1133: =IF(C1133="","",IF(C1133>0,IF(J1133<30,"Normal",IF(J1133<60,"Especially Mentioned",IF(J1133<90,"Substandard",IF(J1133<=180,"Doubtful",IF(J1133>180,"Loss","0"))))),"Not Applicable")) -> Not Applicable
A1134: 2026/08/28 | B1134: 2026/08/28 | C1134: 0 | D1134: 2050 | E1134: OT26240TZ0127413 | F1134: OT26240TZ0127413 | G1134: a7d2ecc8-54b2-4e1e-bf9c-53e8cb4f3c67 | H1134: NMIBTZTZXXX NMIBTZTZ | I1134: 103 SCCT | J1134: =IF(A1134="","",A$5-A1134) -> 59 | K1134: =IF(J1134="","",IF(J1134<4,"0-3 Days",IF(J1134<31,"4-30 Days",IF(J1134<61,"31-60 Days",IF(J1134<=90,"61-90 Days",IF(J1134>90,"Above 90 Days","0")))))) -> 31-60 Days | L1134: =IF(C1134="","",IF(C1134>0,IF(J1134<30,"Normal",IF(J1134<60,"Especially Mentioned",IF(J1134<90,"Substandard",IF(J1134<=180,"Doubtful",IF(J1134>180,"Loss","0"))))),"Not Applicable")) -> Not Applicable
A1135: 2026/08/28 | B1135: 2026/08/28 | C1135: 0 | D1135: 500 | E1135: P260828C00001341 | F1135: P260828C00001341 | G1135: 7df19e57-2d7c-4b9c-b6ab-e2ba47bc9dfb | H1135: NMIBTZTZXXX NMIBTZTZ | I1135: 103 SCCT | J1135: =IF(A1135="","",A$5-A1135) -> 59 | K1135: =IF(J1135="","",IF(J1135<4,"0-3 Days",IF(J1135<31,"4-30 Days",IF(J1135<61,"31-60 Days",IF(J1135<=90,"61-90 Days",IF(J1135>90,"Above 90 Days","0")))))) -> 31-60 Days | L1135: =IF(C1135="","",IF(C1135>0,IF(J1135<30,"Normal",IF(J1135<60,"Especially Mentioned",IF(J1135<90,"Substandard",IF(J1135<=180,"Doubtful",IF(J1135>180,"Loss","0"))))),"Not Applicable")) -> Not Applicable
A1136: 2026/08/28 | B1136: 2026/08/28 | C1136: 0 | D1136: 1000 | E1136: TZAAO24026HR9BL | F1136: cf103140-b913-4b9c-9a3f-e72b91b9aaa | G1136: defae1c6-dc2e-42eb-a316-07d30773f607 | H1136: BARCTZTZXXX NMIBTZTZ | I1136: 103 SCCT | J1136: =IF(A1136="","",A$5-A1136) -> 59 | K1136: =IF(J1136="","",IF(J1136<4,"0-3 Days",IF(J1136<31,"4-30 Days",IF(J1136<61,"31-60 Days",IF(J1136<=90,"61-90 Days",IF(J1136>90,"Above 90 Days","0")))))) -> 31-60 Days | L1136: =IF(C1136="","",IF(C1136>0,IF(J1136<30,"Normal",IF(J1136<60,"Especially Mentioned",IF(J1136<90,"Substandard",IF(J1136<=180,"Doubtful",IF(J1136>180,"Loss","0"))))),"Not Applicable")) -> Not Applicable
A1137: 2026/08/28 | B1137: 2026/08/28 | C1137: 0 | D1137: 12225.26 | E1137: OT26240TZ0127586 | F1137: OT26240TZ0127586 | G1137: 3ac8a144-2bf9-447b-90ed-2166cd0b549b | H1137: NMIBTZTZXXX NMIBTZTZ | I1137: 103 SCCT | J1137: =IF(A1137="","",A$5-A1137) -> 59 | K1137: =IF(J1137="","",IF(J1137<4,"0-3 Days",IF(J1137<31,"4-30 Days",IF(J1137<61,"31-60 Days",IF(J1137<=90,"61-90 Days",IF(J1137>90,"Above 90 Days","0")))))) -> 31-60 Days | L1137: =IF(C1137="","",IF(C1137>0,IF(J1137<30,"Normal",IF(J1137<60,"Especially Mentioned",IF(J1137<90,"Substandard",IF(J1137<=180,"Doubtful",IF(J1137>180,"Loss","0"))))),"Not Applicable")) -> Not Applicable
A1138: 2026/08/28 | B1138: 2026/08/28 | C1138: 20000000 | D1138: 0 | E1138: NMBFUN2808026/01 | F1138: NMBFUN2808026/01 | G1138: 94681744-40d0-4a60-a49c-4baa716d752f | H1138: NMIBTZTZ TANZTZTXXXX | I1138: 202 FIT | J1138: =IF(A1138="","",A$5-A1138) -> 59 | K1138: =IF(J1138="","",IF(J1138<4,"0-3 Days",IF(J1138<31,"4-30 Days",IF(J1138<61,"31-60 Days",IF(J1138<=90,"61-90 Days",IF(J1138>90,"Above 90 Days","0")))))) -> 31-60 Days | L1138: =IF(C1138="","",IF(C1138>0,IF(J1138<30,"Normal",IF(J1138<60,"Especially Mentioned",IF(J1138<90,"Substandard",IF(J1138<=180,"Doubtful",IF(J1138>180,"Loss","0"))))),"Not Applicable")) -> Especially Mentioned
A1139: 2026/08/28 | B1139: 2026/08/28 | C1139: 0 | D1139: 1000 | E1139: FT26238WVXZ81 | F1139: FT26238WVXZ81 | G1139: e967f6ef-01b9-4651-9cd9-40bef8d838eb | H1139: NMIBTZTZXXX NMIBTZTZ | I1139: 103 SCCT | J1139: =IF(A1139="","",A$5-A1139) -> 59 | K1139: =IF(J1139="","",IF(J1139<4,"0-3 Days",IF(J1139<31,"4-30 Days",IF(J1139<61,"31-60 Days",IF(J1139<=90,"61-90 Days",IF(J1139>90,"Above 90 Days","0")))))) -> 31-60 Days | L1139: =IF(C1139="","",IF(C1139>0,IF(J1139<30,"Normal",IF(J1139<60,"Especially Mentioned",IF(J1139<90,"Substandard",IF(J1139<=180,"Doubtful",IF(J1139>180,"Loss","0"))))),"Not Applicable")) -> Not Applicable
... A1178: 2026/08/28 | B1178: 2026/08/28 | C1178: 0 | D1178: 2050 | E1178: TZ1RTGF262400838 | F1178: NOTPROVIDED | G1178: a9915217-d13f-4d7a-8580-49765a2fe2a9 | H1178: NMIBTZTZXXX NMIBTZTZ | I1178: 103 SCCT | J1178: =IF(A1178="","",A$5-A1178) -> 59 | K1178: =IF(J1178="","",IF(J1178<4,"0-3 Days",IF(J1178<31,"4-30 Days",IF(J1178<61,"31-60 Days",IF(J1178<=90,"61-90 Days",IF(J1178>90,"Above 90 Days","0")))))) -> 31-60 Days | L1178: =IF(C1178="","",IF(C1178>0,IF(J1178<30,"Normal",IF(J1178<60,"Especially Mentioned",IF(J1178<90,"Substandard",IF(J1178<=180,"Doubtful",IF(J1178>180,"Loss","0"))))),"Not Applicable")) -> Not Applicable
A1179: 2026/08/28 | B1179: 2026/08/28 | C1179: 0 | D1179: 29429.88 | E1179: 260828TA039807 | F1179: 260828TA039807 | H1179: TACHTZTZ NMIBTZTZ | I1179: 701 NSI | J1179: =IF(A1179="","",A$5-A1179) -> 59 | K1179: =IF(J1179="","",IF(J1179<4,"0-3 Days",IF(J1179<31,"4-30 Days",IF(J1179<61,"31-60 Days",IF(J1179<=90,"61-90 Days",IF(J1179>90,"Above 90 Days","0")))))) -> 31-60 Days | L1179: =IF(C1179="","",IF(C1179>0,IF(J1179<30,"Normal",IF(J1179<60,"Especially Mentioned",IF(J1179<90,"Substandard",IF(J1179<=180,"Doubtful",IF(J1179>180,"Loss","0"))))),"Not Applicable")) -> Not Applicable
A1180: 2026/08/28 | B1180: 2026/08/28 | C1180: 0 | D1180: 495.6 | E1180: TZAAO24026HPKB9 | F1180: 16b20c0b-2e56-417c-852e-1507e867eab | G1180: 7891e5d1-fc02-4b15-82de-b7f0a0857cce | H1180: BARCTZTZXXX NMIBTZTZ | I1180: 103 SCCT | J1180: =IF(A1180="","",A$5-A1180) -> 59 | K1180: =IF(J1180="","",IF(J1180<4,"0-3 Days",IF(J1180<31,"4-30 Days",IF(J1180<61,"31-60 Days",IF(J1180<=90,"61-90 Days",IF(J1180>90,"Above 90 Days","0")))))) -> 31-60 Days | L1180: =IF(C1180="","",IF(C1180>0,IF(J1180<30,"Normal",IF(J1180<60,"Especially Mentioned",IF(J1180<90,"Substandard",IF(J1180<=180,"Doubtful",IF(J1180>180,"Loss","0"))))),"Not Applicable")) -> Not Applicable
A1181: 2026/08/29 | B1181: 2026/08/29 | C1181: 0 | D1181: 600 | E1181: P260829C00001539 | F1181: P260829C00001539 | G1181: 27d11d46-9b73-4231-b4c6-4af377c58521 | H1181: NMIBTZTZXXX NMIBTZTZ | I1181: 103 SCCT | J1181: =IF(A1181="","",A$5-A1181) -> 58 | K1181: =IF(J1181="","",IF(J1181<4,"0-3 Days",IF(J1181<31,"4-30 Days",IF(J1181<61,"31-60 Days",IF(J1181<=90,"61-90 Days",IF(J1181>90,"Above 90 Days","0")))))) -> 31-60 Days | L1181: =IF(C1181="","",IF(C1181>0,IF(J1181<30,"Normal",IF(J1181<60,"Especially Mentioned",IF(J1181<90,"Substandard",IF(J1181<=180,"Doubtful",IF(J1181>180,"Loss","0"))))),"Not Applicable")) -> Not Applicable
...
